Workbook

Sheet Amendment EUR (2)
A1: !!Please insert lines under the sub-headings if necessary!! | C1: !! Pay attention not to erase formulas in the blue cells !! | H1: If this table is filled up, no need to fill in the "project budget in euros" sheet | N1: Do not fill in this table in euros - it will fill up automatically !! Pay attention not to erase formulas in the cells !! | U1: Careful : if you add extra lines, remember to copy formulas !
A2: Name of the person in charge of the budget | O2: Name of the person in charge of the budget | P2: =C2 -> 0
A3: Name of the applicant NGO | C3: Sened Organization | H3: Euro exchange rate € / USD | J3: 0.047 | K3: <If necessary update the local currency exchange rate in J3 cell | O3: Name of the applicant NGO | P3: =C3 -> Sened Organization
A4: Project title | K4: Control columns | O4: Project title | P4: =C4 -> 0 | X4: Control columns
B5: Expenditure related to the project Recommendations | C5: Unit | D5: Number of units | E5: Unit cost in EUR | F5: Total cost in EUR | H5: Year 1 in TRY | I5: Year 2 in TRY | J5: Year 3 in TRY | K5: Total 3 years in TRY | L5: Discrepancy (column F-K) must equal zero | O5: Expenditure related to the project Recommendations | P5: Unit | Q5: Number of units | R5: Unit cost (euros) | S5: Total cost (euros) | U5: Year 1 (euros) | V5: Year 2 (euros) | W5: Year 3 (euros) | X5: Total 3 years (euros) | Y5: Discrepancy (column S-X) must equal zero | AA5: Sened Contribution | AD5: 45505 | AE5: 45536 | AF5: 45566 | AG5: 45597 | AH5: 45627 | AI5: 45658 | AJ5: 45689 | AK5: TOTAL EXPENSES | AL5: % | AM5: Remaining
A6: 1 | B6: Human resources dedicated to the project | N6: 1 | O6: Human resources dedicated to the project
A7: 1.1 | B7: Salaries and employer's contributions | N7: 1.1 | O7: Salaries and employer's contributions
B8: Salary for coordination
A9: 1.1.01 | B9: IT and Media Officer (50%) TR | C9: per month | D9: 6 | E9: 1650 | AA9: =D9*E9*AD9 -> 4950 | AD9: 0.5
A10: 1.1.02 | B10: MHPSS Technical Specialist (10%) TR | C10: per month | D10: 6 | E10: 3500 | N10: 1.1.4 | O10: MHPSS Technical Specialist (5%) TR | P10: per month | Q10: 6 | R10: =E10*$J$3 -> 164.5 | S10: =R10*Q10 -> 987 | U10: =H10*$J$3 -> 0 | V10: =I10*$J$3 -> 0 | W10: =J10*$J$3 -> 0 | X10: =SUM(U10:W10) -> 0 | Y10: =S10-X10 -> 987 | Z10: =SUM(F10:F16)/F72 -> 0 | AA10: =D10*E10*AD10 -> 2100 | AD10: 0.1
A11: 1.1.03 | B11: Supply Chain Coordinator (10%) TR | C11: per month | D11: 6 | E11: 3100 | N11: 1.1.5 | O11: Supply Chain Coordinator (5%) TR | P11: per month | Q11: 6 | R11: =E11*$J$3 -> 145.7 | S11: =R11*Q11 -> 874.2 | U11: =H11*$J$3 -> 0 | V11: =I11*$J$3 -> 0 | W11: =J11*$J$3 -> 0 | X11: =SUM(U11:W11) -> 0 | Y11: =S11-X11 -> 874.2 | AA11: =D11*E11*AD11 -> 1860 | AD11: 0.1
A12: 1.1.04 | B12: Project Coordinator (10%) TR | C12: per month | D12: 6 | E12: 3100 | N12: 1.1.6 | O12: Project Coordinator (5%) TR | P12: per month | Q12: 6 | R12: =E12*$J$3 -> 145.7 | S12: =R12*Q12 -> 874.2 | U12: =H12*$J$3 -> 0 | V12: =I12*$J$3 -> 0 | W12: =J12*$J$3 -> 0 | X12: =SUM(U12:W12) -> 0 | Y12: =S12-X12 -> 874.2 | AA12: =D12*E12*AD12 -> 1860 | AD12: 0.1
A13: 1.1.05 | B13: Inclusion Technical Specialist (10%) SY | C13: per month | D13: 6 | E13: 850 | N13: 1.1.13 | O13: Inclusion Technical Specialist (5%) SY | P13: per month | Q13: 6 | R13: =E13*$J$3 -> 39.95 | S13: =R13*Q13 -> 239.7 | U13: =H13*$J$3 -> 0 | V13: =I13*$J$3 -> 0 | W13: =J13*$J$3 -> 0 | X13: =SUM(U13:W13) -> 0 | Y13: =S13-X13 -> 239.7 | AA13: =D13*E13*AD13 -> 510 | AD13: 0.1
A14: 1.1.06 | B14: MEAL Coordinator (10%) TR | C14: per month | D14: 6 | E14: 3100 | N14: 1.1.10 | O14: MEAL Coordinator (5%) TR | P14: per month | Q14: 6 | R14: =E14*$J$3 -> 145.7 | S14: =R14*Q14 -> 874.2 | U14: =H14*$J$3 -> 0 | V14: =I14*$J$3 -> 0 | W14: =J14*$J$3 -> 0 | X14: =SUM(U14:W14) -> 0 | Y14: =S14-X14 -> 874.2 | AA14: =D14*E14*AD14 -> 1860 | AD14: 0.1
A15: 1.1.07 | B15: HR Coordinator (10%) TR | C15: per month | D15: 6 | E15: 3100 | N15: 1.1.8 | O15: HR Coordinator (20%) TR | P15: per month | Q15: 6 | R15: =E15*$J$3 -> 145.7 | S15: =R15*Q15 -> 874.2 | U15: =H15*$J$3 -> 0 | V15: =I15*$J$3 -> 0 | W15: =J15*$J$3 -> 0 | X15: =SUM(U15:W15) -> 0 | Y15: =S15-X15 -> 874.2 | AA15: =D15*E15*AD15 -> 1860 | AD15: 0.1
A16: 1.1.08 | B16: Finance Coordiantor (10%) TR | C16: per month | D16: 6 | E16: 3100 | AA16: =D16*E16*AD16 -> 1860 | AD16: 0.1
B17: Salary for operational staff
A18: 1.1.08 | B18: Project Officer (100%) TR | C18: per month | D18: 5 | E18: 1650 | F18: =E18*D18 -> 8250 | N18: 1.1.11 | O18: =B18 -> Project Officer (100%) TR | P18: per month | Q18: 6 | R18: =E18*$J$3 -> 77.55 | S18: =R18*Q18 -> 465.3 | U18: =H18*$J$3 -> 0 | V18: =I18*$J$3 -> 0 | W18: =J18*$J$3 -> 0 | X18: =SUM(U18:W18) -> 0 | Y18: =S18-X18 -> 465.3 | Z18: =SUM(F18:F31)/F72 -> 0.54 | AD18: 1441.423 | AE18: 1368.7681 | AF18: 1354.1584 | AG18: 1392.9992 | AH18: 1415.5261 | AI18: 1812.287 | AJ18: 1807.6306 | AK18: =SUM(AD18:AJ18) -> 10592.792 | AL18: =AK18/F18 -> 1.2839748 | AM18: =F18-AK18 -> -2342.7925
A19: 1.1.09 | B19: Finance Assistant (100%) TR | C19: per month | D19: 5 | E19: 800 | F19: =E19*D19 -> 4000 | N19: 1.1.7 | O19: Finance Officer (20%) TR | P19: per month | Q19: 6 | R19: =E19*$J$3 -> 37.6 | S19: =R19*Q19 -> 225.6 | U19: =H19*$J$3 -> 0 | V19: =I19*$J$3 -> 0 | W19: =J19*$J$3 -> 0 | X19: =SUM(U19:W19) -> 0 | Y19: =S19-X19 -> 225.6 | AD19: 333.03423 | AE19: 1060.317 | AF19: 1048.8569 | AG19: -1.238812 | AH19: 0 | AI19: 1432.8779 | AJ19: 1429.4088 | AK19: =SUM(AD19:AJ19) -> 5303.256 | AL19: =AK19/F19 -> 1.325814 | AM19: =F19-AK19 -> -1303.256
A20: 1.1.10 | B20: Supply Assistant (100%) TR | C20: per month | D20: 5 | E20: 800 | F20: =E20*D20 -> 4000 | AD20: 0 | AE20: 1368.7681 | AF20: 1354.1584 | AG20: -0.9802656 | AH20: 0 | AI20: 1285.4684 | AJ20: 1280.4479 | AK20: =SUM(AD20:AJ20) -> 5287.8625 | AL20: =AK20/F20 -> 1.3219656 | AM20: =F20-AK20 -> -1287.8625
A21: 1.1.11 | B21: Child safeguarding specalist (15%) | C21: per month | D21: 5 | E21: 300 | F21: =E21*D21 -> 1500 | AD21: 0 | AE21: 743.45667 | AF21: 565.01871 | AG21: 329.782 | AH21: 119.86201 | AI21: 374.34356 | AJ21: 377.45982 | AK21: =SUM(AD21:AJ21) -> 2509.9228 | AL21: =AK21/F21 -> 1.6732818 | AM21: =F21-AK21 -> -1009.9228
A22: 1.1.12 | B22: Case Manager*1 (100%) - SY | C22: per month | D22: 5 | E22: 700 | F22: =E22*D22 -> 3500 | N22: 1.1.14 | O22: Case Manager*2 (100%) - SY | P22: per month | Q22: 10 | R22: =E22*$J$3 -> 32.9 | S22: =R22*Q22 -> 329 | U22: =H22*$J$3 -> 0 | V22: =I22*$J$3 -> 0 | W22: =J22*$J$3 -> 0 | X22: =SUM(U22:W22) -> 0 | Y22: =S22-X22 -> 329 | AD22: 0 | AE22: 572.34207 | AF22: 588.36843 | AG22: 607.02616 | AH22: 622.74934 | AI22: 686.61608 | AJ22: 689.31955 | AK22: =SUM(AD22:AJ22) -> 3766.4216 | AL22: =AK22/F22 -> 1.0761205 | AM22: =F22-AK22 -> -266.42162
A23: 1.1.13 | B23: Case Officer*1 ( 100%)-SY | C23: per month | D23: 5 | E23: 500 | F23: =E23*D23 -> 2500 | AD23: 0 | AE23: 136.63482 | AF23: 452.5911 | AG23: 186.77728 | AH23: 0 | AI23: 1110.6884 | AJ23: 586.3686 | AK23: =SUM(AD23:AJ23) -> 2473.0602 | AL23: =AK23/F23 -> 0.98922408 | AM23: =F23-AK23 -> 26.9398
A24: 1.1.14 | B24: PSS Officer*2 (100%) - SY | C24: per month | D24: 10 | E24: 500 | F24: =E24*D24 -> 5000 | N24: 1.1.15 | O24: PSS Officer*2 (100%) - SY | P24: per month | Q24: 10 | R24: =E24*$J$3 -> 23.5 | S24: =R24*Q24 -> 235 | AD24: 0 | AE24: 15.187659 | AF24: 0 | AG24: 0 | AH24: 0 | AI24: 902.58752 | AJ24: 1014.8791 | AK24: =SUM(AD24:AJ24) -> 1932.6543 | AL24: =AK24/F24 -> 0.38653085 | AM24: =F24-AK24 -> 3067.3457
A25: 1.1.15 | B25: Inclusion Sr.Officer (100%) SY | C25: per month | D25: 5 | E25: 650 | F25: =E25*D25 -> 3250 | AD25: 0 | AE25: 0 | AF25: 588.36843 | AG25: 607.02616 | AH25: 622.74934 | AI25: 686.61608 | AJ25: 689.31955 | AK25: =SUM(AD25:AJ25) -> 3194.0795 | AL25: =AK25/F25 -> 0.98279371 | AM25: =F25-AK25 -> 55.92045
A26: 1.1.16 | B26: SNR Officer*1 (100%) - SY | C26: per month | D26: 5 | E26: 500 | F26: =E26*D26 -> 2500 | N26: 1.1.16 | O26: SNR Officer*2 (100%) - SY | P26: per month | Q26: 10 | R26: =E26*$J$3 -> 23.5 | S26: =R26*Q26 -> 235 | U26: =H26*$J$3 -> 0 | V26: =I26*$J$3 -> 0 | W26: =J26*$J$3 -> 0 | X26: =SUM(U26:W26) -> 0 | Y26: =S26-X26 -> 235 | AD26: 0 | AE26: 0 | AF26: 0 | AG26: 217.90066 | AH26: 479.03795 | AI26: 541.55634 | AJ26: 543.68866 | AK26: =SUM(AD26:AJ26) -> 1782.1836 | AL26: =AK26/F26 -> 0.71287344 | AM26: =F26-AK26 -> 717.81639
A27: 1.1.17 | B27: Case Worker*4 (100%) - SY | C27: per month | D27: 20 | E27: 375 | F27: =E27*D27 -> 7500 | N27: 1.1.17 | O27: Case Worker*4 (100%) - SY | P27: per month | Q27: 20 | R27: =E27*$J$3 -> 17.625 | S27: =R27*Q27 -> 352.5 | U27: =H27*$J$3 -> 0 | V27: =I27*$J$3 -> 0 | W27: =J27*$J$3 -> 0 | X27: =SUM(U27:W27) -> 0 | Y27: =S27-X27 -> 352.5 | AD27: 0 | AE27: 456.97358 | AF27: 1024.3526 | AG27: 980.58072 | AH27: 1341.3063 | AI27: 1189.4898 | AJ27: 1205.7373 | AK27: =SUM(AD27:AJ27) -> 6198.4402 | AL27: =AK27/F27 -> 0.8264587 | AM27: =F27-AK27 -> 1301.5598
A28: 1.1.18 | B28: PSS Facilitator*4 (100%) - SY | C28: per month | D28: 20 | E28: 375 | F28: =E28*D28 -> 7500 | N28: 1.1.18 | O28: PSS Facilitator*4 (100%) - SY | P28: per month | Q28: 20 | R28: =E28*$J$3 -> 17.625 | S28: =R28*Q28 -> 352.5 | U28: =H28*$J$3 -> 0 | V28: =I28*$J$3 -> 0 | W28: =J28*$J$3 -> 0 | X28: =SUM(U28:W28) -> 0 | Y28: =S28-X28 -> 352.5 | AD28: 0 | AE28: 0 | AF28: 464.65718 | AG28: 1263.8719 | AH28: 1330.1224 | AI28: 1438.1213 | AJ28: 1196.663 | AK28: =SUM(AD28:AJ28) -> 5693.4357 | AL28: =AK28/F28 -> 0.75912476 | AM28: =F28-AK28 -> 1806.5643
A29: 1.1.19 | B29: Media Officer (100%) - SY | C29: per month | D29: 5 | E29: 500 | F29: =E29*D29 -> 2500 | N29: 1.1.21 | O29: Media Officer (100%) - SY | P29: per month | Q29: 5 | R29: =E29*$J$3 -> 23.5 | S29: =R29*Q29 -> 117.5 | U29: =H29*$J$3 -> 0 | V29: =I29*$J$3 -> 0 | W29: =J29*$J$3 -> 0 | X29: =SUM(U29:W29) -> 0 | Y29: =S29-X29 -> 117.5 | AD29: 0 | AE29: 440.26174 | AF29: 452.5911 | AG29: 466.9432 | AH29: 479.03795 | AI29: 541.55634 | AJ29: 543.68866 | AK29: =SUM(AD29:AJ29) -> 2924.079 | AL29: =AK29/F29 -> 1.1696316 | AM29: =F29-AK29 -> -424.07899
A30: 1.1.21 | B30: Driver (100%) - SY | C30: per month | D30: 5 | E30: 200 | F30: =E30*D30 -> 1000 | N30: 1.1.22 | O30: Receptioinst (100%) - SY | P30: per month | Q30: 5 | R30: =E30*$J$3 -> 9.4 | S30: =R30*Q30 -> 47 | U30: =H30*$J$3 -> 0 | V30: =I30*$J$3 -> 0 | W30: =J30*$J$3 -> 0 | X30: =SUM(U30:W30) -> 0 | Y30: =S30-X30 -> 47 | AD30: 0 | AE30: 0 | AF30: 30.194754 | AG30: 911.7546 | AH30: 191.61518 | AI30: 251.43687 | AJ30: 252.42688 | AK30: =SUM(AD30:AJ30) -> 1637.4283 | AL30: =AK30/F30 -> 1.6374283 | AM30: =F30-AK30 -> -637.42828
A31: 1.1.22 | B31: Cleaner (100%) - SY | C31: per month | D31: 5 | E31: 200 | F31: =E31*D31 -> 1000 | N31: 1.1.24 | O31: Cleaner (100%) - SY | P31: per month | Q31: 5 | R31: =E31*$J$3 -> 9.4 | S31: =R31*Q31 -> 47 | U31: =H31*$J$3 -> 0 | V31: =I31*$J$3 -> 0 | W31: =J31*$J$3 -> 0 | X31: =SUM(U31:W31) -> 0 | Y31: =S31-X31 -> 47 | AD31: 0 | AE31: 0 | AF31: 0 | AG31: 101.16486 | AH31: 239.51898 | AI31: 299.79012 | AJ31: 0 | AK31: =SUM(AD31:AJ31) -> 640.47396 | AL31: =AK31/F31 -> 0.64047396 | AM31: =F31-AK31 -> 359.52604
A32: 1.2 | B32: Honoraires experts | N32: 1.2 | O32: Honoraires experts
A33: 1.2.1 | F33: =E33*D33 -> 0 | H33: =F33 -> 0 | K33: =SUM(H33:J33) -> 0 | L33: =F33-K33 -> 0 | Q33: =$D33 -> 0 | R33: =E33*$J$3 -> 0 | S33: =R33*Q33 -> 0 | U33: =H33*$J$3 -> 0 | V33: =I33*$J$3 -> 0 | W33: =J33*$J$3 -> 0 | X33: =SUM(U33:W33) -> 0 | Y33: =S33-X33 -> 0
F34: =E34*D34 -> 0 | K34: =SUM(H34:J34) -> 0 | L34: =F34-K34 -> 0 | Q34: =$D34 -> 0 | R34: =E34*$J$3 -> 0 | S34: =R34*Q34 -> 0 | U34: =H34*$J$3 -> 0 | V34: =I34*$J$3 -> 0 | W34: =J34*$J$3 -> 0 | X34: =SUM(U34:W34) -> 0 | Y34: =S34-X34 -> 0
A35: 1.3 | B35: Per diem food and accomodation | N35: 1.3 | O35: Per diem food and accomodation
A36: 1.3.1
F37: =E37*D37 -> 0 | K37: =SUM(H37:J37) -> 0 | L37: =F37-K37 -> 0 | Q37: =$D37 -> 0 | R37: =E37*$J$3 -> 0 | S37: =R37*Q37 -> 0 | U37: =H37*$J$3 -> 0 | V37: =I37*$J$3 -> 0 | W37: =J37*$J$3 -> 0 | X37: =SUM(U37:W37) -> 0 | Y37: =S37-X37 -> 0
A38: Sub-total 1 Human resources of the project | F38: =SUM(F9:F37) -> 54000 | H38: =SUM(H10:H37) -> 0 | I38: =SUM(I10:I37) -> 0 | J38: =SUM(J10:J37) -> 0 | K38: =SUM(K10:K37) -> 0 | L38: =SUM(L10:L37) -> 0 | N38: Sub-total 1 Human resources of the project | S38: =SUM(S10:S37) -> 7129.9 | U38: =SUM(U10:U37) -> 0 | V38: =SUM(V10:V37) -> 0 | W38: =SUM(W10:W37) -> 0 | X38: =SUM(X10:X37) -> 0 | Y38: =SUM(Y10:Y37) -> 6894.9 | AA38: =SUM(AA9:AA37) -> 16860
A39: 2 | B39: Travel costs | N39: 2 | O39: Travel costs
A40: 2.1 | B40: 2 Cars for mobile team and benfiaries | C40: per month | D40: 2 | E40: 6000 | H40: 0 | K40: =SUM(H40:J40) -> 0 | L40: =F40-K40 -> 0 | N40: 2.1 | O40: Rental two Cars + running cost (purchase and Running cost) | P40: per month | Q40: =$D40 -> 2 | R40: =E40*$J$3 -> 282 | S40: =R40*Q40 -> 564 | U40: =H40*$J$3 -> 0 | V40: =I40*$J$3 -> 0 | W40: =J40*$J$3 -> 0 | X40: =SUM(U40:W40) -> 0 | Y40: =S40-X40 -> 564 | AA40: =D40*E40*1 -> 12000
A41: 2.2 | B41: Fuel for 2 cars | C41: per month | D41: 5 | E41: 200 | F41: =E41*D41 -> 1000 | AD41: 0 | AE41: 131.67448 | AF41: 126.72551 | AG41: 166.72064 | AH41: 530.24645 | AI41: 738.7475 | AJ41: 456.03993 | AK41: =SUM(AD41:AJ41) -> 2150.1545 | AL41: =AK41/F41 -> 2.1501545 | AM41: =F41-AK41 -> -1150.1545
A42: 2.3 | B42: Travel cost from Turkey to Syria for management and Support staff | C42: per month | D42: 5 | E42: 200 | H42: 0 | K42: =SUM(H42:J42) -> 0 | L42: =F42-K42 -> 0 | N42: 2.2 | O42: Rental Minibus + running cost | P42: per month | Q42: =$D42 -> 5 | R42: =E42*$J$3 -> 9.4 | S42: =R42*Q42 -> 47 | U42: =H42*$J$3 -> 0 | V42: =I42*$J$3 -> 0 | W42: =J42*$J$3 -> 0 | X42: =SUM(U42:W42) -> 0 | Y42: =S42-X42 -> 47 | AA42: =D42*E42*1 -> 1000
A43: Sub- total 2 Travel costs | F43: =SUM(F40:F42) -> 1000 | H43: =SUM(H40:H42) -> 0 | I43: =SUM(I40:I42) -> 0 | J43: =SUM(J40:J42) -> 0 | K43: =SUM(K40:K42) -> 0 | L43: =SUM(L40:L42) -> 0 | N43: Sub- total 2 Travel costs | S43: =SUM(S40:S42) -> 611 | T43: =SUM(T40:T42) -> 0 | U43: =SUM(U40:U42) -> 0 | V43: =SUM(V40:V42) -> 0 | W43: =SUM(W40:W42) -> 0 | X43: =SUM(X40:X42) -> 0 | Y43: =SUM(Y40:Y42) -> 611 | AA43: =SUM(AA40:AA42) -> 13000
A44: 3 | B44: Equipment (material and supplies) | N44: 3 | O44: Equipment (material and supplies)
A45: 3.1.1 | B45: Laptops | C45: per item | D45: 6 | E45: 750 | K45: =SUM(H45:J45) -> 0 | L45: =F45-K45 -> 0 | N45: 3.1.1 | O45: Laptops | P45: per item | Q45: =$D45 -> 6 | R45: =E45*$J$3 -> 35.25 | S45: =R45*Q45 -> 211.5 | U45: =H45*$J$3 -> 0 | V45: =I45*$J$3 -> 0 | W45: =J45*$J$3 -> 0 | X45: =SUM(U45:W45) -> 0 | Y45: =S45-X45 -> 211.5 | AA45: =D45*E45*1 -> 4500
A46: 3.1.2 | B46: Mobile phones | C46: per item | D46: 6 | E46: 350 | K46: =SUM(H46:J46) -> 0 | L46: =F46-K46 -> 0 | N46: 3.1.2 | O46: Tablets | P46: per item | Q46: =$D46 -> 6 | R46: =E46*$J$3 -> 16.45 | S46: =R46*Q46 -> 98.7 | U46: =H46*$J$3 -> 0 | V46: =I46*$J$3 -> 0 | W46: =J46*$J$3 -> 0 | X46: =SUM(U46:W46) -> 0 | Y46: =S46-X46 -> 98.7 | AA46: =D46*E46*1 -> 2100
A47: 3.1.3 | B47: Projector | C47: per item | D47: 1 | E47: 600 | AA47: =D47*E47*1 -> 600
A48: 3.1.4 | B48: Water dispenser | C48: per item | D48: 2 | E48: 200 | AA48: =D48*E48*1 -> 400
A49: 3.1.6 | B49: Supplies and Stationary | C49: lumpsum | D49: 1 | E49: 400 | F49: =E49*D49 -> 400 | K49: =SUM(H49:J49) -> 0 | L49: =F49-K49 -> 400 | N49: 3.1.5 | O49: Stationary | P49: lumpsum | Q49: =$D49 -> 1 | R49: =E49*$J$3 -> 18.8 | S49: =R49*Q49 -> 18.8 | U49: =H49*$J$3 -> 0 | V49: =I49*$J$3 -> 0 | W49: =J49*$J$3 -> 0 | X49: =SUM(U49:W49) -> 0 | Y49: =S49-X49 -> 18.8 | Z49: =A49&"."&B49 -> 3.1.6.Supplies and Stationary | AD49: 0 | AE49: 0 | AF49: 0 | AG49: 0 | AH49: 0 | AI49: 0 | AJ49: 321.1089 | AK49: =SUM(AD49:AJ49) -> 321.1089 | AL49: =AK49/F49 -> 0.80277226 | AM49: =F49-AK49 -> 78.891097
A50: 3.1.7 | B50: Refreshment for activities | C50: lumpsum | D50: 1 | E50: 400 | F50: =E50*D50 -> 400 | K50: =SUM(H50:J50) -> 0 | L50: =F50-K50 -> 400 | N50: 3.1.6 | O50: Refreshment for activities | P50: per participant | Q50: =$D50 -> 1 | R50: =E50*$J$3 -> 18.8 | S50: =R50*Q50 -> 18.8 | U50: =H50*$J$3 -> 0 | V50: =I50*$J$3 -> 0 | W50: =J50*$J$3 -> 0 | X50: =SUM(U50:W50) -> 0 | Y50: =S50-X50 -> 18.8 | Z50: =A50&"."&B50 -> 3.1.7.Refreshment for activities | AD50: 0 | AE50: 0 | AF50: 0 | AG50: 0 | AH50: 0 | AI50: 104.55791 | AJ50: 96.81261 | AK50: =SUM(AD50:AJ50) -> 201.37052 | AL50: =AK50/F50 -> 0.5034263 | AM50: =F50-AK50 -> 198.62948
A51: 3.1.8 | B51: PSS Kits for chilren | C51: lumpsum | D51: 1 | E51: 7500 | F51: =E51*D51 -> 7500 | K51: =SUM(H51:J51) -> 0 | L51: =F51-K51 -> 7500 | N51: 3.1.7 | O51: Printings and IEC materials | P51: per participant | Q51: =$D51 -> 1 | R51: =E51*$J$3 -> 352.5 | S51: =R51*Q51 -> 352.5 | U51: =H51*$J$3 -> 0 | V51: =I51*$J$3 -> 0 | W51: =J51*$J$3 -> 0 | X51: =SUM(U51:W51) -> 0 | Y51: =S51-X51 -> 352.5 | Z51: =A51&"."&B51 -> 3.1.8.PSS Kits for chilren | AD51: 0 | AE51: 0 | AF51: 0 | AG51: 0 | AH51: 0 | AI51: 5862.3474 | AJ51: 0 | AK51: =SUM(AD51:AJ51) -> 5862.3474 | AL51: =AK51/F51 -> 0.78164632 | AM51: =F51-AK51 -> 1637.6526
A52: 3.1.9 | B52: PSS Kits for adults | C52: lumpsum | D52: 1 | E52: 7500 | F52: =E52*D52 -> 7500 | K52: =SUM(H52:J52) -> 0 | L52: =F52-K52 -> 7500 | N52: 3.1.9 | O52: PSS Kits for adults | P52: lumpsum | Q52: =$D52 -> 1 | R52: =E52*$J$3 -> 352.5 | S52: =R52*Q52 -> 352.5 | U52: =H52*$J$3 -> 0 | V52: =I52*$J$3 -> 0 | W52: =J52*$J$3 -> 0 | X52: =SUM(U52:W52) -> 0 | Y52: =S52-X52 -> 352.5 | Z52: =A52&"."&B52 -> 3.1.9.PSS Kits for adults | AD52: 0 | AE52: 0 | AF52: 0 | AG52: 0 | AH52: 0 | AI52: 4678.1812 | AJ52: 0 | AK52: =SUM(AD52:AJ52) -> 4678.1812 | AL52: =AK52/F52 -> 0.6237575 | AM52: =F52-AK52 -> 2821.8188
A53: 3.1.10 | B53: Printing MEAL materials | C53: lumpsum | D53: 6 | E53: 84.848485 | F53: =E53*D53 -> 509.09091 | K53: =SUM(H53:J53) -> 0 | L53: =F53-K53 -> 509.09091 | N53: 3.1.10 | O53: PSS Package for group sessions for adult | P53: lumpsum | Q53: =$D53 -> 6 | R53: =E53*$J$3 -> 3.9878788 | S53: =R53*Q53 -> 23.927273 | U53: =H53*$J$3 -> 0 | V53: =I53*$J$3 -> 0 | W53: =J53*$J$3 -> 0 | X53: =SUM(U53:W53) -> 0 | Y53: =S53-X53 -> 23.927273 | Z53: =A53&"."&B53 -> 3.1.10.Printing MEAL materials | AD53: 0 | AE53: 0 | AF53: 0 | AG53: 261.30141 | AH53: 199.2039 | AI53: 0 | AJ53: 0 | AK53: =SUM(AD53:AJ53) -> 460.50531 | AL53: =AK53/F53 -> 0.90456401 | AM53: =F53-AK53 -> 48.585594
A54: 3.1.11 | B54: Montessori tools | C54: lumpsum | D54: 1 | E54: 1000 | F54: =E54*D54 -> 1000 | K54: =SUM(H54:J54) -> 0 | L54: =F54-K54 -> 1000 | N54: 3.1.11 | O54: Recreational activities material | P54: lumpsum | Q54: =$D54 -> 1 | R54: =E54*$J$3 -> 47 | S54: =R54*Q54 -> 47 | U54: =H54*$J$3 -> 0 | V54: =I54*$J$3 -> 0 | W54: =J54*$J$3 -> 0 | X54: =SUM(U54:W54) -> 0 | Y54: =S54-X54 -> 47 | Z54: =A54&"."&B54 -> 3.1.11.Montessori tools | AD54: 0 | AE54: 0 | AF54: 0 | AG54: 522.64952 | AH54: 0 | AI54: 0 | AJ54: 0 | AK54: =SUM(AD54:AJ54) -> 522.64952 | AL54: =AK54/F54 -> 0.52264952 | AM54: =F54-AK54 -> 477.35048
A55: Sub-total 3 Material and supplies | F55: =SUM(F45:F54) -> 17309.091 | H55: =SUM(H45:H54) -> 0 | I55: =SUM(I45:I54) -> 0 | J55: =SUM(J45:J54) -> 0 | K55: =SUM(K45:K54) -> 0 | L55: =SUM(L45:L54) -> 17309.091 | N55: Sub-total 3 Material and supplies | S55: =SUM(S45:S54) -> 1123.7273 | U55: =SUM(U45:U54) -> 0 | V55: =SUM(V45:V54) -> 0 | W55: =SUM(W45:W54) -> 0 | X55: =SUM(X45:X54) -> 0 | Y55: =SUM(Y45:Y54) -> 1123.7273 | AA55: =SUM(AA45:AA54) -> 7600
A56: 4 | N56: 4 | O56: Other costs
A57: 4.1 | B57: Other costs | K57: =SUM(H57:J57) -> 0 | L57: =F57-K57 -> 0 | N57: 4.1 | O57: Rent Community Center in Gaziantep (50%) | P57: per month | Q57: =D57 -> 0 | R57: =E57*$J$3 -> 0 | S57: =R57*Q57 -> 0 | U57: =H57*$J$3 -> 0 | V57: =I57*$J$3 -> 0 | W57: =J57*$J$3 -> 0 | X57: =SUM(U57:W57) -> 0 | Y57: =S57-X57 -> 0
A58: 4.2 | B58: Rent Community Center in A'zaz (50%) | C58: per month | D58: 6 | E58: 375 | K58: =SUM(H58:J58) -> 0 | L58: =F58-K58 -> 0 | N58: 4.2 | O58: Office rehabilitation setup | P58: times | Q58: =$D58 -> 6 | R58: =E58*$J$3 -> 17.625 | S58: =R58*Q58 -> 105.75 | U58: =H58*$J$3 -> 0 | V58: =I58*$J$3 -> 0 | W58: =J58*$J$3 -> 0 | X58: =SUM(U58:W58) -> 0 | Y58: =S58-X58 -> 105.75 | AA58: =D58*E58 -> 2250
A59: 4.3 | B59: Office running cost A'zaz with Mobile bills forproject staff | C59: per month | D59: 6 | E59: 183.33333 | F59: =E59*D59 -> 1100 | K59: =SUM(H59:J59) -> 0 | L59: =F59-K59 -> 1100 | N59: 4.3 | O59: Office running cost Gaziantep | P59: per month | Q59: =$D59 -> 6 | R59: =E59*$J$3 -> 8.6166667 | S59: =R59*Q59 -> 51.7 | U59: =H59*$J$3 -> 0 | V59: =I59*$J$3 -> 0 | W59: =J59*$J$3 -> 0 | X59: =SUM(U59:W59) -> 0 | Y59: =S59-X59 -> 51.7 | Z59: =A59&"."&B59 -> 4.3.Office running cost A'zaz with Mobile bills forproject staff | AD59: =SUMIFS('[1]Transactions List'!$L:$L,'[1]Transactions List'!$O:$O,"8",'[1]Transactions List'!$N:$N,"2024",'[1]Transactions List'!$B:$B,'Amendment EUR (2)'!$A46) -> 0 | AE59: =SUMIFS('[1]Transactions List'!$L:$L,'[1]Transactions List'!$O:$O,"9",'[1]Transactions List'!$N:$N,"2024",'[1]Transactions List'!$B:$B,'Amendment EUR (2)'!$A59) -> 0 | AF59: =SUMIFS('[1]Transactions List'!$L:$L,'[1]Transactions List'!$O:$O,"10",'[1]Transactions List'!$N:$N,"2024",'[1]Transactions List'!$B:$B,'Amendment EUR (2)'!$A59) -> 0 | AG59: =SUMIFS('[1]Transactions List'!$L:$L,'[1]Transactions List'!$O:$O,"11",'[1]Transactions List'!$N:$N,"2024",'[1]Transactions List'!$B:$B,'Amendment EUR (2)'!$A59) -> 2163.9107 | AH59: =SUMIFS('[1]Transactions List'!$L:$L,'[1]Transactions List'!$O:$O,"12",'[1]Transactions List'!$N:$N,"2024",'[1]Transactions List'!$B:$B,'Amendment EUR (2)'!$A59) -> 0 | AI59: =SUMIFS('[1]Transactions List'!$L:$L,'[1]Transactions List'!$O:$O,"1",'[1]Transactions List'!$N:$N,"2025",'[1]Transactions List'!$B:$B,'Amendment EUR (2)'!$A59) -> 2227.3651 | AJ59: =SUMIFS('[1]Transactions List'!$L:$L,'[1]Transactions List'!$O:$O,"2",'[1]Transactions List'!$N:$N,"2025",'[1]Transactions List'!$B:$B,'Amendment EUR (2)'!$A59) -> 158.25127 | AK59: =SUM(AD59:AJ59) -> 4549.5271 | AL59: =AK59/F59 -> 4.1359337 | AM59: =F59-AK59 -> -3449.5271
A60: 4.5 | B60: ECF | C60: per beneficiary | D60: 350 | E60: 50 | F60: =E60*D60 -> 17500 | K60: =SUM(H60:J60) -> 0 | L60: =F60-K60 -> 17500 | N60: 4.5 | O60: Case management support | P60: per beneficiary | Q60: =$D60 -> 350 | R60: =E60*$J$3 -> 2.35 | S60: =R60*Q60 -> 822.5 | U60: =H60*$J$3 -> 0 | V60: =I60*$J$3 -> 0 | W60: =J60*$J$3 -> 0 | X60: =SUM(U60:W60) -> 0 | Y60: =S60-X60 -> 822.5 | Z60: =A60&"."&B60 -> 4.5.ECF | AD60: =SUMIFS('[1]Transactions List'!$L:$L,'[1]Transactions List'!$O:$O,"8",'[1]Transactions List'!$N:$N,"2024",'[1]Transactions List'!$B:$B,'Amendment EUR (2)'!$A47) -> 0 | AE60: =SUMIFS('[1]Transactions List'!$L:$L,'[1]Transactions List'!$O:$O,"9",'[1]Transactions List'!$N:$N,"2024",'[1]Transactions List'!$B:$B,'Amendment EUR (2)'!$A60) -> 0 | AF60: =SUMIFS('[1]Transactions List'!$L:$L,'[1]Transactions List'!$O:$O,"11",'[1]Transactions List'!$N:$N,"2024",'[1]Transactions List'!$B:$B,'Amendment EUR (2)'!$A60) -> 0 | AG60: =SUMIFS('[1]Transactions List'!$L:$L,'[1]Transactions List'!$O:$O,"11",'[1]Transactions List'!$N:$N,"2024",'[1]Transactions List'!$B:$B,'Amendment EUR (2)'!$A60) -> 0 | AH60: =SUMIFS('[1]Transactions List'!$L:$L,'[1]Transactions List'!$O:$O,"12",'[1]Transactions List'!$N:$N,"2024",'[1]Transactions List'!$B:$B,'Amendment EUR (2)'!$A60) -> 89.342895 | AI60: =SUMIFS('[1]Transactions List'!$L:$L,'[1]Transactions List'!$O:$O,"1",'[1]Transactions List'!$N:$N,"2025",'[1]Transactions List'!$B:$B,'Amendment EUR (2)'!$A60) -> 3071.1679 | AJ60: =SUMIFS('[1]Transactions List'!$L:$L,'[1]Transactions List'!$O:$O,"2",'[1]Transactions List'!$N:$N,"2025",'[1]Transactions List'!$B:$B,'Amendment EUR (2)'!$A60) -> 15066.645 | AK60: =SUM(AD60:AJ60) -> 18227.156 | AL60: =AK60/F60 -> 1.0415518 | AM60: =F60-AK60 -> -727.15582
A61: 4.6 | B61: Case management support | F61: =E61*D61 -> 0 | K61: =SUM(H61:J61) -> 0 | L61: =F61-K61 -> 0 | N61: 4.6 | O61: Training Cost for 20 participant (Venue + lunch + coffee break) | P61: training | Q61: =$D61 -> 0 | R61: =E61*$J$3 -> 0 | S61: =R61*Q61 -> 0 | U61: =H61*$J$3 -> 0 | V61: =I61*$J$3 -> 0 | W61: =J61*$J$3 -> 0 | X61: =SUM(U61:W61) -> 0 | Y61: =S61-X61 -> 0 | AD61: =SUMIFS('[1]Transactions List'!$L:$L,'[1]Transactions List'!$O:$O,"8",'[1]Transactions List'!$N:$N,"2024",'[1]Transactions List'!$B:$B,'Amendment EUR (2)'!$A48) -> 0 | AE61: =SUMIFS('[1]Transactions List'!$L:$L,'[1]Transactions List'!$O:$O,"9",'[1]Transactions List'!$N:$N,"2024",'[1]Transactions List'!$B:$B,'Amendment EUR (2)'!$A61) -> 0 | AF61: =SUMIFS('[1]Transactions List'!$L:$L,'[1]Transactions List'!$O:$O,"11",'[1]Transactions List'!$N:$N,"2024",'[1]Transactions List'!$B:$B,'Amendment EUR (2)'!$A61) -> 0 | AG61: =SUMIFS('[1]Transactions List'!$L:$L,'[1]Transactions List'!$O:$O,"11",'[1]Transactions List'!$N:$N,"2024",'[1]Transactions List'!$B:$B,'Amendment EUR (2)'!$A61) -> 0 | AH61: =SUMIFS('[1]Transactions List'!$L:$L,'[1]Transactions List'!$O:$O,"12",'[1]Transactions List'!$N:$N,"2024",'[1]Transactions List'!$B:$B,'Amendment EUR (2)'!$A61) -> 0 | AI61: =SUMIFS('[1]Transactions List'!$L:$L,'[1]Transactions List'!$O:$O,"1",'[1]Transactions List'!$N:$N,"2025",'[1]Transactions List'!$B:$B,'Amendment EUR (2)'!$A61) -> 0 | AJ61: =SUMIFS('[1]Transactions List'!$L:$L,'[1]Transactions List'!$O:$O,"2",'[1]Transactions List'!$N:$N,"2025",'[1]Transactions List'!$B:$B,'Amendment EUR (2)'!$A61) -> 0 | AK61: =SUM(AD61:AJ61) -> 0 | AL61: =AK61/F61 -> #DIV/0! | AM61: =F61-AK61 -> 0
A62: 4.7 | F62: =E62*D62 -> 0 | K62: =SUM(H62:J62) -> 0 | L62: =F62-K62 -> 0 | N62: 4.7 | O62: Accomodation of trainers | P62: per day | Q62: =$D62 -> 0 | R62: =E62*$J$3 -> 0 | S62: =R62*Q62 -> 0 | U62: =H62*$J$3 -> 0 | V62: =I62*$J$3 -> 0 | W62: =J62*$J$3 -> 0 | X62: =SUM(U62:W62) -> 0 | Y62: =S62-X62 -> 0 | AD62: =SUMIFS('[1]Transactions List'!$L:$L,'[1]Transactions List'!$O:$O,"8",'[1]Transactions List'!$N:$N,"2024",'[1]Transactions List'!$B:$B,'Amendment EUR (2)'!$A49) -> 0 | AE62: =SUMIFS('[1]Transactions List'!$L:$L,'[1]Transactions List'!$O:$O,"9",'[1]Transactions List'!$N:$N,"2024",'[1]Transactions List'!$B:$B,'Amendment EUR (2)'!$A62) -> 0 | AF62: =SUMIFS('[1]Transactions List'!$L:$L,'[1]Transactions List'!$O:$O,"11",'[1]Transactions List'!$N:$N,"2024",'[1]Transactions List'!$B:$B,'Amendment EUR (2)'!$A62) -> 0 | AG62: =SUMIFS('[1]Transactions List'!$L:$L,'[1]Transactions List'!$O:$O,"11",'[1]Transactions List'!$N:$N,"2024",'[1]Transactions List'!$B:$B,'Amendment EUR (2)'!$A62) -> 0 | AH62: =SUMIFS('[1]Transactions List'!$L:$L,'[1]Transactions List'!$O:$O,"12",'[1]Transactions List'!$N:$N,"2024",'[1]Transactions List'!$B:$B,'Amendment EUR (2)'!$A62) -> 0 | AI62: =SUMIFS('[1]Transactions List'!$L:$L,'[1]Transactions List'!$O:$O,"1",'[1]Transactions List'!$N:$N,"2025",'[1]Transactions List'!$B:$B,'Amendment EUR (2)'!$A62) -> 0 | AJ62: =SUMIFS('[1]Transactions List'!$L:$L,'[1]Transactions List'!$O:$O,"2",'[1]Transactions List'!$N:$N,"2025",'[1]Transactions List'!$B:$B,'Amendment EUR (2)'!$A62) -> 0 | AK62: =SUM(AD62:AJ62) -> 0 | AL62: =AK62/F62 -> #DIV/0! | AM62: =F62-AK62 -> 0
A63: 4.8 | F63: =E63*D63 -> 0 | K63: =SUM(H63:J63) -> 0 | L63: =F63-K63 -> 0 | N63: 4.8 | O63: Child friendly space | P63: lumpsum | Q63: =$D63 -> 0 | R63: =E63*$J$3 -> 0 | S63: =R63*Q63 -> 0 | U63: =H63*$J$3 -> 0 | V63: =I63*$J$3 -> 0 | W63: =J63*$J$3 -> 0 | X63: =SUM(U63:W63) -> 0 | Y63: =S63-X63 -> 0 | AD63: =SUMIFS('[1]Transactions List'!$L:$L,'[1]Transactions List'!$O:$O,"8",'[1]Transactions List'!$N:$N,"2024",'[1]Transactions List'!$B:$B,'Amendment EUR (2)'!$A50) -> 0 | AE63: =SUMIFS('[1]Transactions List'!$L:$L,'[1]Transactions List'!$O:$O,"9",'[1]Transactions List'!$N:$N,"2024",'[1]Transactions List'!$B:$B,'Amendment EUR (2)'!$A63) -> 0 | AF63: =SUMIFS('[1]Transactions List'!$L:$L,'[1]Transactions List'!$O:$O,"11",'[1]Transactions List'!$N:$N,"2024",'[1]Transactions List'!$B:$B,'Amendment EUR (2)'!$A63) -> 0 | AG63: =SUMIFS('[1]Transactions List'!$L:$L,'[1]Transactions List'!$O:$O,"11",'[1]Transactions List'!$N:$N,"2024",'[1]Transactions List'!$B:$B,'Amendment EUR (2)'!$A63) -> 0 | AH63: =SUMIFS('[1]Transactions List'!$L:$L,'[1]Transactions List'!$O:$O,"12",'[1]Transactions List'!$N:$N,"2024",'[1]Transactions List'!$B:$B,'Amendment EUR (2)'!$A63) -> 0 | AI63: =SUMIFS('[1]Transactions List'!$L:$L,'[1]Transactions List'!$O:$O,"1",'[1]Transactions List'!$N:$N,"2025",'[1]Transactions List'!$B:$B,'Amendment EUR (2)'!$A63) -> 0 | AJ63: =SUMIFS('[1]Transactions List'!$L:$L,'[1]Transactions List'!$O:$O,"2",'[1]Transactions List'!$N:$N,"2025",'[1]Transactions List'!$B:$B,'Amendment EUR (2)'!$A63) -> 0 | AK63: =SUM(AD63:AJ63) -> 0 | AL63: =AK63/F63 -> #DIV/0! | AM63: =F63-AK63 -> 0
A64: 4.9 | F64: =E64*D64 -> 0 | K64: =SUM(H64:J64) -> 0 | L64: =F64-K64 -> 0 | N64: 4.9 | O64: Hotline | P64: per month | Q64: =$D64 -> 0 | R64: =E64*$J$3 -> 0 | S64: =R64*Q64 -> 0 | U64: =H64*$J$3 -> 0 | V64: =I64*$J$3 -> 0 | W64: =J64*$J$3 -> 0 | X64: =SUM(U64:W64) -> 0 | Y64: =S64-X64 -> 0 | AD64: =SUMIFS('[1]Transactions List'!$L:$L,'[1]Transactions List'!$O:$O,"8",'[1]Transactions List'!$N:$N,"2024",'[1]Transactions List'!$B:$B,'Amendment EUR (2)'!$A51) -> 0 | AE64: =SUMIFS('[1]Transactions List'!$L:$L,'[1]Transactions List'!$O:$O,"9",'[1]Transactions List'!$N:$N,"2024",'[1]Transactions List'!$B:$B,'Amendment EUR (2)'!$A64) -> 0 | AF64: =SUMIFS('[1]Transactions List'!$L:$L,'[1]Transactions List'!$O:$O,"11",'[1]Transactions List'!$N:$N,"2024",'[1]Transactions List'!$B:$B,'Amendment EUR (2)'!$A64) -> 0 | AG64: =SUMIFS('[1]Transactions List'!$L:$L,'[1]Transactions List'!$O:$O,"11",'[1]Transactions List'!$N:$N,"2024",'[1]Transactions List'!$B:$B,'Amendment EUR (2)'!$A64) -> 0 | AH64: =SUMIFS('[1]Transactions List'!$L:$L,'[1]Transactions List'!$O:$O,"12",'[1]Transactions List'!$N:$N,"2024",'[1]Transactions List'!$B:$B,'Amendment EUR (2)'!$A64) -> 0 | AI64: =SUMIFS('[1]Transactions List'!$L:$L,'[1]Transactions List'!$O:$O,"1",'[1]Transactions List'!$N:$N,"2025",'[1]Transactions List'!$B:$B,'Amendment EUR (2)'!$A64) -> 0 | AJ64: =SUMIFS('[1]Transactions List'!$L:$L,'[1]Transactions List'!$O:$O,"2",'[1]Transactions List'!$N:$N,"2025",'[1]Transactions List'!$B:$B,'Amendment EUR (2)'!$A64) -> 0 | AK64: =SUM(AD64:AJ64) -> 0 | AL64: =AK64/F64 -> #DIV/0! | AM64: =F64-AK64 -> 0
A65: Sub-total 4 Other costs | F65: =SUM(F57:F64) -> 18600 | H65: =SUM(H57:H64) -> 0 | I65: =SUM(I57:I64) -> 0 | J65: =SUM(J57:J64) -> 0 | K65: =SUM(K57:K64) -> 0 | L65: =SUM(L57:L64) -> 18600 | N65: Sub-total 4 Other costs | S65: =SUM(S57:S64) -> 979.95 | U65: =SUM(U57:U64) -> 0 | V65: =SUM(V57:V64) -> 0 | W65: =SUM(W57:W64) -> 0 | X65: =SUM(X57:X64) -> 0 | Y65: =SUM(Y57:Y64) -> 979.95 | AA65: =SUM(AA57:AA64) -> 2250 | AK65: =SUM(AD65:AJ65) -> 0 | AL65: =AK65/F65 -> 0 | AM65: =F65-AK65 -> 18600
A66: Sub-total 5 Administrative costs (10%) | F66: =(F38+F43+F55+F65)*10% -> 9090.9091 | H66: =(H38+H43+H55+H65)*7% -> 0 | K66: =SUM(H66:J66) -> 0 | L66: =F66-K66 -> 9090.9091 | N66: Sub-total 5 Administrative costs | S66: =(S38+S43+S55+S65)*7% -> 689.12041 | U66: =(U38+U43+U55+U65)*7% -> 0 | V66: =(V38+V43+V55+V65)*10% -> 0 | W66: =(W38+W43+W55+W65)*10% -> 0 | X66: =(X38+X43+X55+X65)*7% -> 0 | Y66: =(Y38+Y43+Y55+Y65)*7% -> 672.67041 | AA66: =(AA38+AA43+AA55+AA65)*10% -> 3971 | AD66: =SUM(AD18:AD65)*10% -> 177.44573 | AE66: =SUM(AE18:AE65)*10% -> 629.43843 | AF66: =SUM(AF18:AF65)*10% -> 805.00414 | AG66: =SUM(AG18:AG65)*10% -> 1017.819 | AH66: =SUM(AH18:AH65)*10% -> 766.03188 | AI66: =SUM(AI18:AI65)*10% -> 2923.5803 | AJ66: =SUM(AJ18:AJ65)*10% -> 2771.5896 | AK66: =SUM(AD66:AJ66) -> 9090.909 | AL66: =AK66/F66 -> 1 | AM66: =F66-AK66 -> 4.1805892e-05
A67: TOTAL DIRECT COSTS OF THE PROJET (1 to 5) | F67: =SUM(F66,F65,F55,F43,F38) -> 100000 | H67: =SUM(H66,H65,H55,H43,H38) -> 0 | I67: =SUM(I66,I65,I55,I43,I38) -> 0 | J67: =SUM(J66,J65,J55,J43,J38) -> 0 | K67: =SUM(K66,K65,K55,K43,K38) -> 0 | L67: =SUM(L66,L65,L55,L43,L38) -> 45000 | N67: TOTAL DIRECT COSTS OF THE PROJET (1 to 5) | S67: =SUM(S66,S65,S55,S43,S38) -> 10533.698 | U67: =SUM(U66,U65,U55,U43,U38) -> 0 | V67: =SUM(V66,V65,V55,V43,V38) -> 0 | W67: =SUM(W66,W65,W55,W43,W38) -> 0 | X67: =SUM(X66,X65,X55,X43,X38) -> 0 | Y67: =SUM(Y66,Y65,Y55,Y43,Y38) -> 10282.248 | AA67: =SUM(AA66,AA65,AA55,AA43,AA38) -> 43681 | AD67: =SUM(AD59:AD66,AD44:AD54,AD41,AD18:AD36) -> 1951.903 | AE67: =SUM(AE59:AE66,AE44:AE54,AE41,AE18:AE36) -> 6923.8227 | AF67: =SUM(AF59:AF66,AF44:AF54,AF41,AF18:AF36) -> 8855.0456 | AG67: =SUM(AG59:AG66,AG44:AG54,AG41,AG18:AG36) -> 11196.009 | AH67: =SUM(AH59:AH66,AH44:AH54,AH41,AH18:AH36) -> 8426.3506 | AI67: =SUM(AI59:AI66,AI44:AI54,AI41,AI18:AI36) -> 32159.383 | AJ67: =SUM(AJ59:AJ66,AJ44:AJ54,AJ41,AJ18:AJ31) -> 30487.486 | AK67: =SUM(AK18:AK66) -> 100000 | AL67: =AK67/F67 -> 1 | AM67: =F67-AK67 -> 0.00045986481
A69: FINANCING PLAN of the PROJECT | C69: Requested* | D69: Raised* | E69: Percentage | F69: Local currency | H69: Year 1 | I69: Year 2 | J69: Year 3 | K69: Total | L69: Discrepancy | N69: FINANCING PLAN of the PROJECT | P69: Requested* | Q69: Raised* | R69: Percentage | S69: euros | U69: Year 1 (euros) | V69: Year 2 (euros) | W69: Year 3 (euros) | X69: Total (euros)
A70: Requested grant to the Fondation de France | E70: =F70/$F$72 -> 0 | H70: 3191480 | K70: =SUM(H70:J70) -> 3191480 | L70: =F70-K70 -> -3191480 | N70: Requested grant to the Fondation de France | R70: =S70/$S$72 -> 0 | S70: =F70*$J$3 -> 0 | U70: =H70*$J$3 -> 149999.56 | V70: =I70*$J$3 -> 0 | W70: =J70*$J$3 -> 0 | X70: =SUM(U70:W70) -> 149999.56 | Y70: =S70-X70 -> -149999.56
C71: 0 | E71: =F71/$F$72 -> 1 | F71: =F67-F70 -> 100000 | H71: =H67-H70 -> -3191480 | K71: =SUM(H71:J71) -> -3191480 | L71: =F71-K71 -> 3291480 | P71: x | R71: =S71/$S$72 -> 1 | S71: =F71*$J$3 -> 4700 | U71: =H71*$J$3 -> -149999.56 | V71: =I71*$J$3 -> 0 | W71: =J71*$J$3 -> 0 | X71: =SUM(U71:W71) -> -149999.56 | Y71: =S71-X71 -> 154699.56
A72: TOTAL RESOURCES | E72: =SUM(E70:E71) -> 1 | F72: =SUM(F70:F71) -> 100000 | H72: =SUM(H70:H71) -> 0 | I72: =SUM(I70:I71) -> 0 | J72: =SUM(J70:J71) -> 0 | K72: =SUM(K70:K71) -> 0 | L72: =SUM(L70:L71) -> 100000 | N72: TOTAL RESOURCES | R72: =SUM(R70:R71) -> 1 | S72: =SUM(S70:S71) -> 4700 | U72: =SUM(U70:U71) -> 0 | V72: =SUM(V70:V71) -> 0 | W72: =SUM(W70:W71) -> 0 | X72: =SUM(X70:X71) -> 0 | Y72: =SUM(Y70:Y71) -> 4700
C73: * tick relevant box | P73: * tick relevant box
A74: Check sum (total direct costs and total income must equal zero) | F74: =+F72-F67 -> 0 | H74: =+H72-H67 -> 0 | I74: =+I72-I67 -> 0 | J74: =+J72-J67 -> 0 | K74: =+K72-K67 -> 0 | L74: =+L72-L67 -> 55000 | N74: Check sum (total direct costs and total income must equal zero) | S74: =+S72-S67 -> -5833.6977 | U74: =+U72-U67 -> 0 | V74: =+V72-V67 -> 0 | W74: =+W72-W67 -> 0 | X74: =+X72-X67 -> 0 | Y74: =+Y72-Y67 -> -5582.2477

Sheet Transactions List
A4: No | B4: Budget | C4: REF | D4: no. of vouch-er | E4: Internal voucher number of the Recipient | F4: Date of voucher | G4: Name of the Recipient from voucher/evidence | H4: Reason for payment (detailled content of voucher/evidence) | I4: Currency of voucher | J4: Amount of voucher | K4: Exchange rate (according EU currency converter or exchange of funds) | L4: Expenditure in the currency of Grant Agreement € | N4: Year | O4: Period
A5: 1 | B5: 1.1.08 | C5: S2400800388 | D5: F09683 | E5: Social Security | F5: 45535 | G5: MOHAMMAD YASSER MALATI | H5: MOHAMMAD YASSER MALATI/ Social Security August-2024 / 100% / ( Total Amount 13363.84 ) | I5: TRY | J5: 13363.84 | K5: 0.02792 | L5: =K5*J5 -> 373.11841 | N5: =YEAR(F5) -> 2024 | O5: =MONTH(F5) -> 8 | P5: 0
A6: 2 | B6: 1.1.08 | C6: S2400800388 | D6: F09696 | E6: Income Tax & Stamp | F6: 45535 | G6: MOHAMMAD YASSER MALATI | H6: MOHAMMAD YASSER MALATI/ Income Tax & Stamp Tax August-2024 / 100% / ( Total Amount 4149.53 ) | I6: TRY | J6: 4149.53 | K6: 0.02792 | L6: =K6*J6 -> 115.85488 | N6: =YEAR(F6) -> 2024 | O6: =MONTH(F6) -> 8 | P6: 0
A7: 3 | B7: 1.1.08 | C7: S2400800388 | D7: F09216 | E7: Salary | F7: 45535 | G7: MOHAMMAD YASSER MALATI | H7: MOHAMMAD YASSER MALATI/ Bank Paid Net Salary August-2024 / 100% / ( Total Amount 34113.53 ) | I7: TRY | J7: 24113.53 | K7: 0.02792 | L7: =K7*J7 -> 673.24976 | N7: =YEAR(F7) -> 2024 | O7: =MONTH(F7) -> 8 | P7: 1
A8: 4 | B8: 1.1.08 | C8: S2400900388 | D8: F07182 | E8: Social Security | F8: 45565 | G8: MOHAMMAD YASSER MALATI | H8: MOHAMMAD YASSER MALATI/ Social Security September-2024 / 100% / ( Total Amount 13466.64 ) | I8: TRY | J8: 13466.64 | K8: 0.02646 | L8: =K8*J8 -> 356.32729 | N8: =YEAR(F8) -> 2024 | O8: =MONTH(F8) -> 9 | P8: 0
A9: 5 | B9: 1.1.08 | C9: S2400900388 | D9: F08575 | E9: Salary | F9: 45565 | G9: MOHAMMAD YASSER MALATI | H9: MOHAMMAD YASSER MALATI/ Bank Paid Net Salary September-2024 / 100% / ( Total Amount 32702.31 ) | I9: TRY | J9: 32702.31 | K9: 0.02646 | L9: =K9*J9 -> 865.30312 | N9: =YEAR(F9) -> 2024 | O9: =MONTH(F9) -> 9 | P9: 0
A10: 6 | B10: 1.1.08 | C10: S2400900388 | D10: F05725 | E10: Income Tax & Stamp | F10: 45565 | G10: MOHAMMAD YASSER MALATI | H10: MOHAMMAD YASSER MALATI/ Income Tax & Stamp Tax September-2024 / 100% / ( Total Amount 5560.76 ) | I10: TRY | J10: 5560.76 | K10: 0.02646 | L10: =K10*J10 -> 147.13771 | N10: =YEAR(F10) -> 2024 | O10: =MONTH(F10) -> 9 | P10: 0
A11: 7 | B11: 1.1.08 | C11: S2400900388 | D11: F07098 | E11: SGK Discount | F11: 45581 | G11: MOHAMMAD YASSER MALATI | H11: MOHAMMAD YASSER MALATI/ SGK Discount September-2024 / 100% / ( Total Amount 55.72 ) | I11: TRY | J11: -55.72 | K11: 0.02622 | L11: =K11*J11 -> -1.4609784 | N11: =YEAR(F11) -> 2024 | O11: =MONTH(F11) -> 10 | P11: 0
A12: 8 | B12: 1.1.08 | C12: S2401000388 | D12: F07075 | E12: Social Security | F12: 45596 | G12: MOHAMMAD YASSER MALATI | H12: MOHAMMAD YASSER MALATI/ Social Security October-2024 / 100% / ( Total Amount 13415 ) | I12: TRY | J12: 13415 | K12: 0.02622 | L12: =K12*J12 -> 351.7413 | N12: =YEAR(F12) -> 2024 | O12: =MONTH(F12) -> 10 | P12: 0
A13: 9 | B13: 1.1.08 | C13: S2401000388 | D13: F06413 | E13: Income Tax & Stamp | F13: 45596 | G13: MOHAMMAD YASSER MALATI | H13: MOHAMMAD YASSER MALATI/ Income Tax & Stamp Tax October-2024 / 100% / ( Total Amount 6159.4 ) | I13: TRY | J13: 6159.4 | K13: 0.02622 | L13: =K13*J13 -> 161.49947 | N13: =YEAR(F13) -> 2024 | O13: =MONTH(F13) -> 10 | P13: 0
A14: 10 | B14: 1.1.08 | C14: S2401000388 | D14: F09894 | E14: Salary | F14: 45596 | G14: MOHAMMAD YASSER MALATI | H14: MOHAMMAD YASSER MALATI/ Bank Paid Net Salary October-2024 / 100% / ( Total Amount 32127.33 ) | I14: TRY | J14: 32127.33 | K14: 0.02622 | L14: =K14*J14 -> 842.37859 | N14: =YEAR(F14) -> 2024 | O14: =MONTH(F14) -> 10 | P14: 0
A15: 11 | B15: 1.1.08 | C15: S2401000388 | D15: F07075 | E15: SGK Discount | F15: 45616 | G15: MOHAMMAD YASSER MALATI | H15: MOHAMMAD YASSER MALATI/ SGK Discount October-2024 / 100% / ( Total Amount 60.6 ) | I15: TRY | J15: -60.6 | K15: 0.02696 | L15: =K15*J15 -> -1.633776 | N15: =YEAR(F15) -> 2024 | O15: =MONTH(F15) -> 11 | P15: 0
A16: 12 | B16: 1.1.08 | C16: S2401100388 | D16: F12225 | E16: Income Tax & Stamp | F16: 45626 | G16: MOHAMMAD YASSER MALATI | H16: MOHAMMAD YASSER MALATI/ Income Tax & Stamp Tax November-2024 / 100% / ( Total Amount 6196.79 ) | I16: TRY | J16: 6196.79 | K16: 0.02696 | L16: =K16*J16 -> 167.06546 | N16: =YEAR(F16) -> 2024 | O16: =MONTH(F16) -> 11 | P16: 0
... A145: 141 | B145: 1.1.21 | C145: S2411000434 | D145: PTT | E145: PTT USD | F145: 45596 | G145: PTT- USD | H145: Commission fees / ABDULHAMID JUMA / Driver / Salary of October-2024 Net Salary Paid by Bank for 5 days / 33.33 USD | I145: USD | J145: 0.3333 | K145: 0.89622 | L145: =K145*J145 -> 0.29871013 | N145: =YEAR(F145) -> 2024 | O145: =MONTH(F145) -> 10 | P145: 0
A146: 142 | B146: 1.1.21 | C146: S2411000623 | D146: PTT | E146: 9502 | F146: 45597 | G146: AZIZ AL AZO-USD | H146: 2 Days fees for driver / dayson 23rd & 24th October 2024 / for a temporary position spanning two working / 30.00 USD x34.2011= 1026.033 Indicative Exchange Rates Announced at 15:30 on 23/10/2024by the Central Bank of Turkey / for -Oct-2024 30.00 USD/DPR1104558734/ Invoice#09502 | I146: TRY | J146: 26 | K146: 0.02696 | L146: =K146*J146 -> 0.70096 | N146: =YEAR(F146) -> 2024 | O146: =MONTH(F146) -> 11 | P146: 1
A147: 143 | B147: 1.1.21 | C147: S2411000635 | D147: PTT | E147: PTT USD | F147: 45624 | G147: PTT- USD | H147: Commission fees / ABDULHAMID JUMA / Driver / Salary of November-2024 Net Salary Paid by Bank / 200 USD | I147: USD | J147: 2 | K147: 0.92464 | L147: =K147*J147 -> 1.84928 | N147: =YEAR(F147) -> 2024 | O147: =MONTH(F147) -> 11 | P147: 0
A148: 144 | B148: 1.1.21 | C148: S2401100194 | D148: PTT | E148: Income Tax & Stamp | F148: 45626 | G148: FIRAS HAJ ISSA | H148: FIRAS HAJ ISSA/ Income Tax & Stamp Tax November-2024 / 100% / ( Total Amount 6196.79 ) 50% | I148: TRY | J148: 3098.39 | K148: 0.02696 | L148: =K148*J148 -> 83.532594 | N148: =YEAR(F148) -> 2024 | O148: =MONTH(F148) -> 11 | P148: 0
A149: 145 | B149: 1.1.21 | C149: S2401100468 | D149: PTT | E149: Salary | F149: 45626 | G149: ABDULHAMID JUMA USD | H149: ABDULHAMID JUMA / Driver / Salary of November-2024 Net Salary Paid by Bank / 200 USD | I149: USD | J149: 200 | K149: 0.92464 | L149: =K149*J149 -> 184.928 | N149: =YEAR(F149) -> 2024 | O149: =MONTH(F149) -> 11 | P149: 0
A150: 146 | B150: 1.1.21 | C150: S2401100194 | D150: PTT | E150: Salary | F150: 45626 | G150: FIRAS HAJ ISSA | H150: FIRAS HAJ ISSA/ Bank Paid Net Salary November-2024 / 100% / ( Total Amount 32066.28 ) 50% | I150: TRY | J150: 16033.14 | K150: 0.02696 | L150: =K150*J150 -> 432.25345 | N150: =YEAR(F150) -> 2024 | O150: =MONTH(F150) -> 11 | P150: 0
A151: 147 | B151: 1.1.21 | C151: S2401100194 | D151: PTT | E151: Social Security | F151: 45626 | G151: FIRAS HAJ ISSA | H151: FIRAS HAJ ISSA/ Social Security November-2024 / 100% / ( Total Amount 13466.64 ) 50% | I151: TRY | J151: 6733.32 | K151: 0.02696 | L151: =K151*J151 -> 181.53031 | N151: =YEAR(F151) -> 2024 | O151: =MONTH(F151) -> 11 | P151: 0
A152: 148 | B152: 1.1.21 | C152: S2411000659 | D152: PTT | E152: Commission fees | F152: 45652 | G152: PTT- USD | H152: 1% PTT Fees of ABDULHAMID JUMA / Driver / Salary of December-2024 Net Salary Paid by Bank / 200 USD | I152: USD | J152: 2 | K152: 0.94859 | L152: =K152*J152 -> 1.89718 | N152: =YEAR(F152) -> 2024 | O152: =MONTH(F152) -> 12 | P152: 0
A153: 149 | B153: 1.1.21 | C153: S2401200468 | D153: PTT | E153: Salary | F153: 45652 | G153: ABDULHAMID JUMA USD | H153: ABDULHAMID JUMA / Driver / Salary of December-2024 Net Salary Paid by Bank / 200 USD | I153: USD | J153: 200 | K153: 0.94859 | L153: =K153*J153 -> 189.718 | N153: =YEAR(F153) -> 2024 | O153: =MONTH(F153) -> 12 | P153: 0
A154: 150 | B154: 1.1.22 | C154: S2411000635 | D154: PTT | E154: PTT USD | F154: 45624 | G154: PTT- USD | H154: Commission fees / MUNTAZER NASIF / Cleaner / Salary of November-2024 Net Salary Paid by Bank for 13 days / 108.33 USD | I154: USD | J154: 1.08 | K154: 0.92464 | L154: =K154*J154 -> 0.9986112 | N154: =YEAR(F154) -> 2024 | O154: =MONTH(F154) -> 11 | P154: 0
A155: 151 | B155: 1.1.22 | C155: S2401100474 | D155: PTT | E155: Salary | F155: 45626 | G155: MUNTAZER NASIF USD | H155: MUNTAZER NASIF / Cleaner / Salary of November-2024 Net Salary Paid by Bank for 13 days / 108.33 USD | I155: USD | J155: 108.33 | K155: 0.92464 | L155: =K155*J155 -> 100.16625 | N155: =YEAR(F155) -> 2024 | O155: =MONTH(F155) -> 11 | P155: 0
A156: 152 | B156: 1.1.22 | C156: S2401200474 | D156: PTT | E156: Salary | F156: 45652 | G156: MUNTAZER NASIF USD | H156: MUNTAZER NASIF / Cleaner / Salary of December-2024 Net Salary Paid by Bank / 250 USD | I156: USD | J156: 250 | K156: 0.94859 | L156: =K156*J156 -> 237.1475 | N156: =YEAR(F156) -> 2024 | O156: =MONTH(F156) -> 12 | P156: 0
A157: 153 | B157: 1.1.22 | C157: S2411000659 | D157: PTT | E157: Commission fees | F157: 45652 | G157: PTT- USD | H157: 1% PTT Fees of MUNTAZER NASIF / Cleaner / Salary of December-2024 Net Salary Paid by Bank / 250 USD | I157: USD | J157: 2.5 | K157: 0.94859 | L157: =K157*J157 -> 2.371475 | N157: =YEAR(F157) -> 2024 | O157: =MONTH(F157) -> 12 | P157: 0
A158: 154 | B158: 2.2 | C158: S2417100007 | D158: 112 | E158: 26263 | F158: 45536 | G158: ABDO AL ASSEAD (PORRIDGE FOR FUEL)-USD | H158: 80 Liters / Fuel Filling for Cm /80* 0,90USD /+ Car Wash Cm/ DPR1714560778 / Invoice#026263 | I158: USD | J158: 75 | K158: 0.90188 | L158: =K158*J158 -> 67.641 | N158: =YEAR(F158) -> 2024 | O158: =MONTH(F158) -> 9 | P158: 0
A159: 155 | B159: 2.2 | C159: S2417100004 | D159: 113 | E159: 26267 | F159: 45542 | G159: ABDO AL ASSEAD (PORRIDGE FOR FUEL)-USD | H159: 70 Liters / Fuel Filling for H1 /70 * 0,9 / + Car Wash Cm + Car Wash H1/ DPR1714560772 /Invoice#026267 | I159: USD | J159: 71 | K159: 0.90188 | L159: =K159*J159 -> 64.03348 | N159: =YEAR(F159) -> 2024 | O159: =MONTH(F159) -> 9 | P159: 0
A160: 156 | B160: 2.2 | C160: S2417100005 | D160: 114 | E160: 26273 | F160: 45566 | G160: ABDO AL ASSEAD (PORRIDGE FOR FUEL)-USD | H160: 41 Liters / Fuel Filling for H1 / 41* 0,9 USD / + Car Wash Cm + Car Wash H1 / DPR1714560737 / Invoice#026273 | I160: USD | J160: 44.9 | K160: 0.89622 | L160: =K160*J160 -> 40.240278 | N160: =YEAR(F160) -> 2024 | O160: =MONTH(F160) -> 10 | P160: 0
A161: 157 | B161: 2.2 | C161: S2417100006 | D161: 115 | E161: 751 | F161: 45567 | G161: MOHAMAD DIAB MALDOAN-USD | H161: 35 Liters / Filling fuel for a cm car /35 L* 0,9 USD / + replacing the cm battery / DPR1714560798 /Invoice#0751 | I161: USD | J161: 96.5 | K161: 0.89622 | L161: =K161*J161 -> 86.48523 | N161: =YEAR(F161) -> 2024 | O161: =MONTH(F161) -> 10 | P161: 0
A162: 158 | B162: 2.2 | C162: S2417100009 | D162: 117 | E162: 3156 | F162: 45599 | G162: MOHAMAD DIAB MALDOAN-USD | H162: 72 Liters / Fuel Filling for H1/ DPR1714561970 / Invoice#3156 | I162: TRY | J162: 2772 | K162: 0.02696 | L162: =K162*J162 -> 74.73312 | N162: =YEAR(F162) -> 2024 | O162: =MONTH(F162) -> 11 | P162: 0
A163: 159 | B163: 2.2 | C163: S2417100010 | D163: 120 | E163: 3154 | F163: 45619 | G163: MOHAMAD DIAB MALDOAN-USD | H163: Engine oil change cm, h1 + transmission oil change cm, h1 / 99.00USD x34.4642 = 3412.00 Indicative Exchange Rates Announced at 15:30 on 22/11/2024by the Central Bank of Turkey / for -Nov-2024 99 USD / DPR17145620100 / Invoice#3154 | I163: TRY | J163: 3412 | K163: 0.02696 | L163: =K163*J163 -> 91.98752 | N163: =YEAR(F163) -> 2024 | O163: =MONTH(F163) -> 11 | P163: 0
A164: 160 | B164: 2.2 | C164: S2417100011 | D164: 139 | E164: 3157 | F164: 45627 | G164: MOHAMAD DIAB MALDOAN-USD | H164: Fuel Filling for H1+ Car Wash H1. Invoice#3157 | I164: TRY | J164: 3060 | K164: 0.02741 | L164: =K164*J164 -> 83.8746 | N164: =YEAR(F164) -> 2024 | O164: =MONTH(F164) -> 12 | P164: 0
A165: 161 | B165: 2.2 | C165: S2417100013 | D165: 153 | E165: 36 | F165: 45643 | G165: ABDULLAH DEK ( ALDEK TRADING COMPANY)-USD | H165: 79 Liters Diesel / 79*39 TRY / Fuel Filling for H1 / INV#0036 | I165: TRY | J165: 3120 | K165: 0.02741 | L165: =K165*J165 -> 85.5192 | N165: =YEAR(F165) -> 2024 | O165: =MONTH(F165) -> 12 | P165: 0
A166: 162 | B166: 2.2 | C166: S2417100014 | D166: 3169 | E166: 3169 | F166: 45650 | G166: MOHAMAD DIAB MALDOAN-USD | H166: 4 cm high quality Cm car wheels.Invoice#3169 | I166: TRY | J166: 13165 | K166: 0.02741 | L166: =K166*J166 -> 360.85265 | N166: =YEAR(F166) -> 2024 | O166: =MONTH(F166) -> 12 | P166: 0
A167: 163 | B167: 3.1.10 | C167: S2417100002 | D167: PTT | E167: 5601 | F167: 45617 | G167: Sham AD.Agency -ABDULMNUM JAWOUYSH- USD | H167: Supplies Materials / Distribute to Beneficiaries / Roll up size 85 * 200 cm + Single side, A5 color Brochures printing + Poster + white wooden box designed for complaints + Regular card cardboard + PSEA Poster + A4 Brochures + PSEA Poster Adult + PSEA A4 Brochures + Table flags + Wall flags /PR#24-SYR-AZA-537 /INV#005601 | I167: USD | J167: 2790.8 | K167: 0.92464 | L167: =K167*J167 -> 2580.4853 | N167: =YEAR(F167) -> 2024 | O167: =MONTH(F167) -> 11 | P167: 1
A168: 164 | B168: 3.1.10 | C168: S2411000635 | D168: PTT | E168: PTT USD | F168: 45624 | G168: PTT- USD | H168: Commission fees / Supplies Materials / Distribute to Beneficiaries / Roll up size 85 * 200 cm + Single side, A5 color Brochures printing + Poster + white wooden box designed for complaints + Regular card cardboard + PSEA Poster + A4 Brochures + PSEA Poster Adult + PSEA A4 Brochures + Table flags + Wall flags /PR#24-SYR-AZA-537 /INV#005601 | I168: USD | J168: 2.798 | K168: 0.92464 | L168: =K168*J168 -> 2.5871427 | N168: =YEAR(F168) -> 2024 | O168: =MONTH(F168) -> 11 | P168: 0
A169: 165 | B169: 3.1.10 | C169: S2411000632 | D169: PTT | E169: 1681 | F169: 45627 | G169: ALI AL SED ALI ( TAYBA TRADING) USD | H169: 25 Vests / for Sened Organization employees in A'zaz and Idlib regions / northwest Syria + carrying / the new Sened Organization logo /PR#24-SYR-AZA-560/INV#1681 | I169: USD | J169: 210 | K169: 0.94859 | L169: =K169*J169 -> 199.2039 | N169: =YEAR(F169) -> 2024 | O169: =MONTH(F169) -> 12 | P169: 0
A170: 166 | B170: 3.1.11 | C170: S2417100003 | D170: PTT | E170: 1682 + 1683 + 1684 + 1685 | F170: 45608 | G170: ALI AL SED ALI ( TAYBA TRADING) USD | H170: One Set Montessori Tools and Materials for Project Activities / including 96 items / PR#24-SYR-AZA-535 /INVS# 1682 + 1683 + 1684 + 1685 | I170: USD | J170: 559.65 | K170: 0.92464 | L170: =K170*J170 -> 517.47478 | N170: =YEAR(F170) -> 2024 | O170: =MONTH(F170) -> 11 | P170: 0
A171: 167 | B171: 3.1.11 | C171: S2411000635 | D171: PTT | E171: PTT USD | F171: 45624 | G171: PTT- USD | H171: Commission fees / One Set Montessori Tools and Materials for Project Activities / including 96 items / PR#24-SYR-AZA-535 /INVS# 1682 + 1683 + 1684 + 1685 | I171: USD | J171: 5.5965 | K171: 0.92464 | L171: =K171*J171 -> 5.1747478 | N171: =YEAR(F171) -> 2024 | O171: =MONTH(F171) -> 11 | P171: 0
A172: 168 | B172: 4.3 | C172: S2417100001 | D172: PTT | E172: 3550 | F172: 45599 | G172: MAHMOUD AMOURİ( AL AMOURI BATTERIES)- USD | H172: Solar energy system and installing / 6 gauge solar panel 300 + Open voltage inverter device 4.2 + 40 M copper cables 10 + Fixed sheet iron + Electrical circuit breakers for protection + Electrical circuit breakers for charging / for Azaz office /PR#24-SYR-AZA-549 /INV#3550 | I172: USD | J172: 576 | K172: 0.92464 | L172: =K172*J172 -> 532.59264 | N172: =YEAR(F172) -> 2024 | O172: =MONTH(F172) -> 11 | P172: 0
A173: 169 | B173: 4.3 | C173: S2417100008 | D173: 156 | E173: 918 | F173: 45622 | G173: ALSHAMI ( MOHAMMED MUSTAFA ALASEEL)-USD | H173: 2 Electric heater with an operating power range of 1000 to 3000 watts / DPR17145621100 / INV#0918 | I173: TRY | J173: 2750 | K173: 0.02696 | L173: =K173*J173 -> 74.14 | N173: =YEAR(F173) -> 2024 | O173: =MONTH(F173) -> 11 | P173: 0
A174: 170 | B174: 4.3 | C174: S2411000635 | D174: PTT | E174: PTT USD | F174: 45624 | G174: PTT- USD | H174: Commission fees / Solar energy system and installing / 6 gauge solar panel 300 + Open voltage inverter device 4.2 + 40 M copper cables 10 + Fixed sheet iron + Electrical circuit breakers for protection + Electrical circuit breakers for charging / for Azaz office /PR#24-SYR-AZA-549 /INV#3550 | I174: USD | J174: 5.76 | K174: 0.92464 | L174: =K174*J174 -> 5.3259264 | N174: =YEAR(F174) -> 2024 | O174: =MONTH(F174) -> 11 | P174: 0
A175: 171 | B175: 4.3 | C175: S2411000631 | D175: PTT | E175: 308 | F175: 45624 | G175: ABDULLAH DERVIS (AL SOROH COMPANY )-USD | H175: 2000 Liters / high-quality heating fuel (Diesel) / for Azaz office / free of impurities + non-cohesive + non-freezing + and without unpleasant odors before or during ignition / For supplies and consumables / 24-SYR-AZA-606 /INV#308 | I175: USD | J175: 1240 | K175: 0.92464 | L175: =K175*J175 -> 1146.5536 | N175: =YEAR(F175) -> 2024 | O175: =MONTH(F175) -> 11 | P175: 0
A176: 172 | B176: 4.5 | C176: S2417100012 | D176: 148 | E176: 157 | F176: 45641 | G176: FADEL MUHAMMED ALHAJ ISSA (AL Fadel Company)-USD | H176: Beneficiary service / diesel heater with accessories + 25 liters of diesel / Invoice#0157 | I176: TRY | J176: 3259.5 | K176: 0.02741 | L176: =K176*J176 -> 89.342895 | N176: =YEAR(F176) -> 2024 | O176: =MONTH(F176) -> 12 | P176: 0
A177: 173 | B177: 4.3 | C177: S2416600084 | D177: 4677 | E177: 4677 | F177: 45601 | G177: SALAH HASANO- USD | H177: 1000 Liters / Monthly water bill for Azaz office covering November / 26.10 USD x34.2757 = 894.595 / for -Nov-2024 26.10 USD. Monthly water subscription to fill 6 water tanks, /DPR1664559727 / Invoice# | I177: TRY | J177: 894.5 | K177: 0.02696 | L177: =K177*J177 -> 24.11572 | N177: =YEAR(F177) -> 2024 | O177: =MONTH(F177) -> 11 | P177: 0
A178: 174 | B178: 4.3 | C178: S2416600080 | D178: 1687 | E178: 1687 | F178: 45601 | G178: ALI AL SED ALI ( TAYBA TRADING) USD | H178: One set of stationery / for daily team use / Blue Pen high quality+ Adhesive tape + Glue Stick equivalent +A4 white paper + High-quality and safe electrical connections + High quality calculator + Plastic folder with a button + Transparent plastic files + A large, high-quality / PR#24-SYR-AZA-492 /INV# | I178: USD | J178: 412.25 | K178: 0.92464 | L178: =K178*J178 -> 381.18284 | N178: =YEAR(F178) -> 2024 | O178: =MONTH(F178) -> 11 | P178: 0
A179: 175 | B179: 1.1.08 | C179: S2500100388 | D179: 229902 | E179: Social Security | F179: 45688 | G179: MOHAMMAD YASSER MALATI | H179: MOHAMMAD YASSER MALATI/ Social Security January-2025 / 100% / ( Total Amount 17647.67 ) | I179: TRY | J179: 17647.67 | K179: 0.02711 | L179: =K179*J179 -> 478.42833 | N179: =YEAR(F179) -> 2025 | O179: =MONTH(F179) -> 1 | P179: 0
A180: 176 | B180: 1.1.08 | C180: S2500100388 | D180: F02310 | E180: Salary | F180: 45688 | G180: MOHAMMAD YASSER MALATI | H180: MOHAMMAD YASSER MALATI/ Bank Paid Net Salary January-2025 / 100% / ( Total Amount 45512.72 ) | I180: TRY | J180: 45512.72 | K180: 0.02711 | L180: =K180*J180 -> 1233.8498 | N180: =YEAR(F180) -> 2025 | O180: =MONTH(F180) -> 1 | P180: 0
A181: 177 | B181: 1.1.08 | C181: S2500100388 | D181: SGK Discount | E181: SGK Discount | F181: 45688 | G181: MOHAMMAD YASSER MALATI | H181: MOHAMMAD YASSER MALATI/ SGK Discount January-2025 / 100% / ( Total Amount 77.38 ) | I181: TRY | J181: -77.38 | K181: 0.02711 | L181: =K181*J181 -> -2.0977718 | N181: =YEAR(F181) -> 2025 | O181: =MONTH(F181) -> 1 | P181: 0
A182: 178 | B182: 1.1.08 | C182: S2500100388 | D182: 581739 | E182: Income Tax & Stamp | F182: 45688 | G182: MOHAMMAD YASSER MALATI | H182: MOHAMMAD YASSER MALATI/ Income Tax & Stamp Tax January-2025 / 100% / ( Total Amount 3766.38 ) | I182: TRY | J182: 3766.38 | K182: 0.02711 | L182: =K182*J182 -> 102.10656 | N182: =YEAR(F182) -> 2025 | O182: =MONTH(F182) -> 1 | P182: 0
A183: 179 | B183: 1.1.08 | C183: S2500200388 | D183: F03316 | E183: Social Security | F183: 45716 | G183: MOHAMMAD YASSER MALATI | H183: MOHAMMAD YASSER MALATI/ Social Security February-2025 / 100% / ( Total Amount 18293.18 ) | I183: TRY | J183: 18293.18 | K183: 0.02687 | L183: =K183*J183 -> 491.53775 | N183: =YEAR(F183) -> 2025 | O183: =MONTH(F183) -> 2 | P183: 0
A184: 180 | B184: 1.1.08 | C184: S2500200388 | D184: SGK Discount | E184: SGK Discount | F184: 45716 | G184: MOHAMMAD YASSER MALATI | H184: MOHAMMAD YASSER MALATI/ SGK Discount February-2025 / 100% / ( Total Amount 251.69 ) | I184: TRY | J184: -251.69 | K184: 0.02687 | L184: =K184*J184 -> -6.7629103 | N184: =YEAR(F184) -> 2025 | O184: =MONTH(F184) -> 2 | P184: 0
A185: 181 | B185: 1.1.08 | C185: S2500200388 | D185: F60092 | E185: Income Tax & Stamp | F185: 45716 | G185: MOHAMMAD YASSER MALATI | H185: MOHAMMAD YASSER MALATI/ Income Tax & Stamp Tax February-2025 / 100% / ( Total Amount 3809.07 ) | I185: TRY | J185: 3809.07 | K185: 0.02687 | L185: =K185*J185 -> 102.34971 | N185: =YEAR(F185) -> 2025 | O185: =MONTH(F185) -> 2 | P185: 0
A186: 182 | B186: 1.1.08 | C186: S2500200388 | D186: F11531 | E186: Salary | F186: 45716 | G186: MOHAMMAD YASSER MALATI | H186: MOHAMMAD YASSER MALATI/ Bank Paid Net Salary February-2025 / 100% / ( Total Amount 45422.63 ) | I186: TRY | J186: 45422.63 | K186: 0.02687 | L186: =K186*J186 -> 1220.5061 | N186: =YEAR(F186) -> 2025 | O186: =MONTH(F186) -> 2 | P186: 0
A187: 183 | B187: 1.1.09 | C187: S2500100364 | D187: 229902 | E187: Social Security | F187: 31-01-2025 | G187: YASEMIN TAHA | H187: YASEMIN TAHA/ Social Security January-2025 / 100% / ( Total Amount 13750.42 ) | I187: TRY | J187: 13750.42 | K187: 0.02711 | L187: =K187*J187 -> 372.77389 | N187: =YEAR(F187) -> 2025 | O187: =MONTH(F187) -> 1 | P187: 0
A188: 184 | B188: 1.1.09 | C188: S2500100364 | D188: SGK Discount | E188: SGK Discount | F188: 31-01-2025 | G188: YASEMIN TAHA | H188: YASEMIN TAHA/ SGK Discount January-2025 / 100% / ( Total Amount 60.3 ) | I188: TRY | J188: -60.3 | K188: 0.02711 | L188: =K188*J188 -> -1.634733 | N188: =YEAR(F188) -> 2025 | O188: =MONTH(F188) -> 1 | P188: 0
A189: 185 | B189: 1.1.09 | C189: S2500100364 | D189: 581739 | E189: Income Tax & Stamp | F189: 31-01-2025 | G189: YASEMIN TAHA | H189: YASEMIN TAHA/ Income Tax & Stamp Tax January-2025 / 100% / ( Total Amount 2158.81 ) | I189: TRY | J189: 2158.81 | K189: 0.02711 | L189: =K189*J189 -> 58.525339 | N189: =YEAR(F189) -> 2025 | O189: =MONTH(F189) -> 1 | P189: 0
A190: 186 | B190: 1.1.09 | C190: S2500100364 | D190: F02487 | E190: Salary | F190: 31-01-2025 | G190: YASEMIN TAHA | H190: YASEMIN TAHA/ Bank Paid Net Salary January-2025 / 100% / ( Total Amount 37005.29 ) | I190: TRY | J190: 37005.29 | K190: 0.02711 | L190: =K190*J190 -> 1003.2134 | N190: =YEAR(F190) -> 2025 | O190: =MONTH(F190) -> 1 | P190: 0
A191: 187 | B191: 1.1.09 | C191: S2500200364 | D191: SGK Discount | E191: SGK Discount | F191: 45716 | G191: YASEMIN TAHA | H191: YASEMIN TAHA/ SGK Discount February-2025 / 100% / ( Total Amount 196.43 ) | I191: TRY | J191: -196.43 | K191: 0.02687 | L191: =K191*J191 -> -5.2780741 | N191: =YEAR(F191) -> 2025 | O191: =MONTH(F191) -> 2 | P191: 0
A192: 188 | B192: 1.1.09 | C192: S2500200364 | D192: Social Security | E192: Social Security | F192: 45716 | G192: YASEMIN TAHA | H192: YASEMIN TAHA/ Social Security February-2025 / 100% / ( Total Amount 14276.93 ) | I192: TRY | J192: 14276.93 | K192: 0.02687 | L192: =K192*J192 -> 383.62111 | N192: =YEAR(F192) -> 2025 | O192: =MONTH(F192) -> 2 | P192: 0
A193: 189 | B193: 1.1.09 | C193: S2500200364 | D193: F60092 | E193: Income Tax & Stamp | F193: 45716 | G193: YASEMIN TAHA | H193: YASEMIN TAHA/ Income Tax & Stamp Tax February-2025 / 100% / ( Total Amount 2201.5 ) | I193: TRY | J193: 2201.5 | K193: 0.02687 | L193: =K193*J193 -> 59.154305 | N193: =YEAR(F193) -> 2025 | O193: =MONTH(F193) -> 2 | P193: 0
A194: 190 | B194: 1.1.09 | C194: S2500200364 | D194: F11804 | E194: Salary | F194: 28-02-2025 | G194: YASEMIN TAHA | H194: YASEMIN TAHA/ Bank Paid Net Salary February-2025 / 100% / ( Total Amount 36915.2 ) | I194: TRY | J194: 36915.2 | K194: 0.02687 | L194: =K194*J194 -> 991.91142 | N194: =YEAR(F194) -> 2025 | O194: =MONTH(F194) -> 2 | P194: 0
A195: 191 | B195: 1.1.10 | C195: S2500100123 | D195: 581739 | E195: Income Tax & Stamp | F195: 45688 | G195: Ismail Kasem | H195: ISMAIL KASEM/ Income Tax & Stamp Tax January-2025 / 50% / ( Total Amount 6968.01 ) | I195: TRY | J195: 3484.01 | K195: 0.02711 | L195: =K195*J195 -> 94.451511 | N195: =YEAR(F195) -> 2025 | O195: =MONTH(F195) -> 1 | P195: 0
A196: 192 | B196: 1.1.10 | C196: S2500100123 | D196: 581739 | E196: Social Security | F196: 45688 | G196: Ismail Kasem | H196: ISMAIL KASEM/ Social Security January-2025 / 50% / ( Total Amount 25409.42 ) | I196: TRY | J196: 1704.71 | K196: 0.02711 | L196: =K196*J196 -> 46.214688 | N196: =YEAR(F196) -> 2025 | O196: =MONTH(F196) -> 1 | P196: 1
A197: 193 | B197: 1.1.10 | C197: S2500100123 | D197: F02290 | E197: Salary | F197: 45688 | G197: Ismail Kasem | H197: ISMAIL KASEM/ Bank Paid Net Salary January-2025 / 50% / ( Total Amount 62456.08 ) | I197: TRY | J197: 31228.04 | K197: 0.02711 | L197: =K197*J197 -> 846.59216 | N197: =YEAR(F197) -> 2025 | O197: =MONTH(F197) -> 1 | P197: 0
A198: 194 | B198: 1.1.10 | C198: S2500200123 | D198: F03316 | E198: Social Security | F198: 45716 | G198: Ismail Kasem | H198: ISMAIL KASEM/ Social Security February-2025 / 50% / ( Total Amount 26291.93 ) | I198: TRY | J198: 13145.96 | K198: 0.02687 | L198: =K198*J198 -> 353.23195 | N198: =YEAR(F198) -> 2025 | O198: =MONTH(F198) -> 2 | P198: 0
A199: 195 | B199: 1.1.10 | C199: S2500200123 | D199: SGK Discount | E199: SGK Discount | F199: 45716 | G199: Ismail Kasem | H199: ISMAIL KASEM/ SGK Discount February-2025 / 50% / ( Total Amount 361.74 ) | I199: TRY | J199: -180.87 | K199: 0.02687 | L199: =K199*J199 -> -4.8599769 | N199: =YEAR(F199) -> 2025 | O199: =MONTH(F199) -> 2 | P199: 0
A200: 196 | B200: 1.1.10 | C200: S2500200123 | D200: F11520 | E200: Salary | F200: 45716 | G200: Ismail Kasem | H200: ISMAIL KASEM/ Bank Paid Net Salary February-2025 / 50% / ( Total Amount 62366 ) | I200: TRY | J200: 31183 | K200: 0.02687 | L200: =K200*J200 -> 837.88721 | N200: =YEAR(F200) -> 2025 | O200: =MONTH(F200) -> 2 | P200: 0
A201: 197 | B201: 1.1.10 | C201: S2500200123 | D201: F60092 | E201: Income Tax & Stamp | F201: 45716 | G201: Ismail Kasem | H201: ISMAIL KASEM/ Income Tax & Stamp Tax February-2025 / 50% / ( Total Amount 7010.7 ) | I201: TRY | J201: 3505.35 | K201: 0.02687 | L201: =K201*J201 -> 94.188755 | N201: =YEAR(F201) -> 2025 | O201: =MONTH(F201) -> 2 | P201: 0
A202: 198 | B202: 1.1.11 | C202: S2500100365 | D202: F02278 | E202: Salary | F202: 45688 | G202: HULUD ELOKUS | H202: HULUD ELOKUS/ Bank Paid Net Salary January-2025 / 25% / ( Total Amount 37831.94 ) / 12 Days | I202: TRY | J202: 9457.99 | K202: 0.02711 | L202: =K202*J202 -> 256.40611 | N202: =YEAR(F202) -> 2025 | O202: =MONTH(F202) -> 1 | P202: 0
A203: 199 | B203: 1.1.11 | C203: S2500100365 | D203: SGK Discount | E203: SGK Discount | F203: 45688 | G203: HULUD ELOKUS | H203: HULUD ELOKUS/ SGK Discount January-2025 / 25% / ( Total Amount 65.13 ) / 12 Days | I203: TRY | J203: -16.28 | K203: 0.02711 | L203: =K203*J203 -> -0.4413508 | N203: =YEAR(F203) -> 2025 | O203: =MONTH(F203) -> 1 | P203: 0
A204: 200 | B204: 1.1.11 | C204: S2500100365 | D204: 581739 | E204: Income Tax & Stamp | F204: 45688 | G204: HULUD ELOKUS | H204: HULUD ELOKUS/ Income Tax & Stamp Tax January-2025 / 25% / ( Total Amount 2613.57 ) / 12 Days | I204: TRY | J204: 653.39 | K204: 0.02711 | L204: =K204*J204 -> 17.713403 | N204: =YEAR(F204) -> 2025 | O204: =MONTH(F204) -> 1 | P204: 0
A205: 201 | B205: 1.1.11 | C205: S2500100365 | D205: 581739 | E205: Social Security | F205: 45688 | G205: HULUD ELOKUS | H205: HULUD ELOKUS/ Social Security January-2025 / 25% / ( Total Amount 14852.9 ) / 12 Days | I205: TRY | J205: 3713.22 | K205: 0.02711 | L205: =K205*J205 -> 100.66539 | N205: =YEAR(F205) -> 2025 | O205: =MONTH(F205) -> 1 | P205: 0
A206: 202 | B206: 1.1.11 | C206: S2500200365 | D206: F60092 | E206: Social Security | F206: 45716 | G206: HULUD ELOKUS | H206: HULUD ELOKUS/ Social Security February-2025 / 25% / ( Total Amount 15491.66 ) / 12 Days | I206: TRY | J206: 3872.91 | K206: 0.02687 | L206: =K206*J206 -> 104.06509 | N206: =YEAR(F206) -> 2025 | O206: =MONTH(F206) -> 2 | P206: 0
A207: 203 | B207: 1.1.11 | C207: S2500200365 | D207: F11506 | E207: Salary | F207: 45716 | G207: HULUD ELOKUS | H207: HULUD ELOKUS/ Bank Paid Net Salary February-2025 / 25% / ( Total Amount 38224.31 ) / 12 Days | I207: TRY | J207: 9556.08 | K207: 0.02687 | L207: =K207*J207 -> 256.77187 | N207: =YEAR(F207) -> 2025 | O207: =MONTH(F207) -> 2 | P207: 0
A208: 204 | B208: 1.1.11 | C208: S2500200365 | D208: SGK Discount | E208: SGK Discount | F208: 45716 | G208: HULUD ELOKUS | H208: HULUD ELOKUS/ SGK Discount February-2025 / 25% / ( Total Amount 213.14 ) / 12 Days | I208: TRY | J208: -53.29 | K208: 0.02687 | L208: =K208*J208 -> -1.4319023 | N208: =YEAR(F208) -> 2025 | O208: =MONTH(F208) -> 2 | P208: 0
A209: 205 | B209: 1.1.11 | C209: S2500200365 | D209: F60092 | E209: Income Tax & Stamp | F209: 45716 | G209: HULUD ELOKUS | H209: HULUD ELOKUS/ Income Tax & Stamp Tax February-2025 / 25% / ( Total Amount 2687.71 ) / 12 Days | I209: TRY | J209: 671.93 | K209: 0.02687 | L209: =K209*J209 -> 18.054759 | N209: =YEAR(F209) -> 2025 | O209: =MONTH(F209) -> 2 | P209: 0
A210: 206 | B210: 1.1.13 | C210: S2400120138 | D210: Salary | E210: Salary | F210: 45658 | G210: MUHAMED VALI- USD | H210: MUHAMED VALI/ Case officer / Bank Paid Net Salary Dec-2024 / 100% / ( Total Amount 550 USD ) | I210: USD | J210: 550 | K210: 0.95749 | L210: =K210*J210 -> 526.6195 | N210: =YEAR(F210) -> 2025 | O210: =MONTH(F210) -> 1 | P210: 0
A211: 207 | B211: 1.1.13 | C211: S2500100138 | D211: Salary | E211: Salary | F211: 45688 | G211: MUHAMED VALI- USD | H211: MUHAMED VALI / Case officer / Bank Paid Net Salary Jan-2025 / 100% / ( Total Amount 610 USD ) | I211: USD | J211: 610 | K211: 0.95749 | L211: =K211*J211 -> 584.0689 | N211: =YEAR(F211) -> 2025 | O211: =MONTH(F211) -> 1 | P211: 0
A212: 208 | B212: 1.1.12 | C212: S2500100449 | D212: PTT- USD | E212: Salary | F212: 45688 | G212: ABDULLAH SALAL USD | H212: ABDULLAH SALAL / Case Manager / Salary of January-2025 Net Salary Paid by Bank / 710 USD | I212: USD | J212: 710 | K212: 0.95749 | L212: =K212*J212 -> 679.8179 | N212: =YEAR(F212) -> 2025 | O212: =MONTH(F212) -> 1 | P212: 0
A213: 209 | B213: 1.1.12 | C213: S2511000011 | D213: PTT- USD | E213: PTT- USD | F213: 45688 | G213: PTT- USD | H213: PTT Transfer fees as 1% for ABDULLAH SALAL / Case Manager / Salary of January-2025 / 7.1 USD | I213: USD | J213: 7.1 | K213: 0.95749 | L213: =K213*J213 -> 6.798179 | N213: =YEAR(F213) -> 2025 | O213: =MONTH(F213) -> 1 | P213: 0
A214: 210 | B214: 1.1.12 | C214: S2500200449 | D214: PTT- USD | E214: Salary | F214: 45716 | G214: ABDULLAH SALAL USD | H214: ABDULLAH SALAL / Case Manager / Salary of February-2025 Net Salary Paid by Bank / 710 USD | I214: USD | J214: 710 | K214: 0.96126 | L214: =K214*J214 -> 682.4946 | N214: =YEAR(F214) -> 2025 | O214: =MONTH(F214) -> 2 | P214: 0
A215: 211 | B215: 1.1.12 | C215: S2511100054 | D215: PTT- USD | E215: PTT- USD | F215: 45716 | G215: PTT- USD | H215: PTT Fees as 1% of ABDULLAH SALAL / Case Manager / Salary of February-2025 Net Salary Paid by Bank / 7.1 USD | I215: USD | J215: 7.1 | K215: 0.96126 | L215: =K215*J215 -> 6.824946 | N215: =YEAR(F215) -> 2025 | O215: =MONTH(F215) -> 2 | P215: 0
A216: 212 | B216: 1.1.13 | C216: S2500200138 | D216: PTT- USD | E216: Salary | F216: 45716 | G216: MUHAMED VALI- USD | H216: MUHAMED VALI / Case officer / Bank Paid Net Salary Feb-2025 / 100% / ( Total Amount 610 USD ) | I216: USD | J216: 610 | K216: 0.96126 | L216: =K216*J216 -> 586.3686 | N216: =YEAR(F216) -> 2025 | O216: =MONTH(F216) -> 2 | P216: 0
A217: 213 | B217: 1.1.14 | C217: S2500100494 | D217: PTT- USD | E217: Salary | F217: 45688 | G217: RIM MHEMD USD | H217: RIM MHEMD / PSS Officer / Salary of January-2025 Net Salary Paid by Bank for 27 days / 504 USD | I217: USD | J217: 504 | K217: 0.95749 | L217: =K217*J217 -> 482.57496 | N217: =YEAR(F217) -> 2025 | O217: =MONTH(F217) -> 1 | P217: 0
... A228: 224 | B228: 1.1.15 | C228: S2500200461 | D228: Salary | E228: Salary | F228: 45716 | G228: AHMAD ABDULLAH USD | H228: AHMAD ABDULLAH / Inclusion Senior Officer / Salary of February-2025 Net Salary Paid by Bank / 710 USD | I228: USD | J228: 710 | K228: 0.96126 | L228: =K228*J228 -> 682.4946 | N228: =YEAR(F228) -> 2025 | O228: =MONTH(F228) -> 2 | P228: 0
A229: 225 | B229: 1.1.16 | C229: S2500100472 | D229: PTT- USD | E229: PTT- USD | F229: 31-01-2025 | G229: EMAN JAQLA USD | H229: EMAN JAQLA / SNR Officer / Salary of January-2025 Net Salary Paid by Bank / 560 USD | I229: USD | J229: 560 | K229: 0.95749 | L229: =K229*J229 -> 536.1944 | N229: =YEAR(F229) -> 2025 | O229: =MONTH(F229) -> 1 | P229: 0
A230: 226 | B230: 1.1.16 | C230: S2511000011 | D230: PTT- USD | E230: PTT- USD | F230: 31-01-2025 | G230: PTT- USD | H230: PTT Transfer fees as 1% for EMAN JAQLA / SNR Officer / Salary of January-2025 / 5.6 USD | I230: USD | J230: 5.6 | K230: 0.95749 | L230: =K230*J230 -> 5.361944 | N230: =YEAR(F230) -> 2025 | O230: =MONTH(F230) -> 1 | P230: 0
A231: 227 | B231: 1.1.16 | C231: S2511100054 | D231: PTT- USD | E231: PTT- USD | F231: 45716 | G231: PTT- USD | H231: PTT Fees as 1% of EMAN JAQLA / SNR Officer / Salary of February-2025 Net Salary Paid by Bank / 5.6 USD | I231: USD | J231: 5.6 | K231: 0.96126 | L231: =K231*J231 -> 5.383056 | N231: =YEAR(F231) -> 2025 | O231: =MONTH(F231) -> 2 | P231: 0
A232: 228 | B232: 1.1.16 | C232: S2500200472 | D232: Salary | E232: Salary | F232: 45716 | G232: EMAN JAQLA USD | H232: EMAN JAQLA / SNR Officer / Salary of February-2025 Net Salary Paid by Bank / 560 USD | I232: USD | J232: 560 | K232: 0.96126 | L232: =K232*J232 -> 538.3056 | N232: =YEAR(F232) -> 2025 | O232: =MONTH(F232) -> 2 | P232: 0
A233: 229 | B233: 1.1.17 | C233: S2511000011 | D233: PTT- USD | E233: PTT- USD | F233: 45688 | G233: PTT- USD | H233: PTT Transfer fees as 1% for MAISAA NAJJAR / Case Worker / Salary of January-2025 / 4.1 USD | I233: USD | J233: 4.1 | K233: 0.95749 | L233: =K233*J233 -> 3.925709 | N233: =YEAR(F233) -> 2025 | O233: =MONTH(F233) -> 1 | P233: 0
A234: 230 | B234: 1.1.17 | C234: S2500100456 | D234: Salary | E234: Salary | F234: 45688 | G234: MAISAA NAJJAR USD | H234: MAISAA NAJJAR / Case Worker / Salary of January-2025 Net Salary Paid by Bank / 410 USD | I234: USD | J234: 410 | K234: 0.95749 | L234: =K234*J234 -> 392.5709 | N234: =YEAR(F234) -> 2025 | O234: =MONTH(F234) -> 1 | P234: 0
A235: 231 | B235: 1.1.17 | C235: S2500100457 | D235: Salary | E235: Salary | F235: 45688 | G235: ASIM EL NEHAR USD | H235: ASIM EL NEHAR / Case Worker / Salary of January-2025 Net Salary Paid by Bank / 410 USD | I235: USD | J235: 410 | K235: 0.95749 | L235: =K235*J235 -> 392.5709 | N235: =YEAR(F235) -> 2025 | O235: =MONTH(F235) -> 1 | P235: 0
A236: 232 | B236: 1.1.17 | C236: S2500100233 | D236: Salary | E236: Salary | F236: 45688 | G236: NASER EL SEYH USD | H236: NASER EL SEYH / Case Worker / Salary of January-2025 Net Salary Paid by Bank / 410 USD | I236: USD | J236: 410 | K236: 0.95749 | L236: =K236*J236 -> 392.5709 | N236: =YEAR(F236) -> 2025 | O236: =MONTH(F236) -> 1 | P236: 0
A237: 233 | B237: 1.1.17 | C237: S2511000011 | D237: PTT- USD | E237: PTT- USD | F237: 45688 | G237: PTT- USD | H237: PTT Transfer fees as 1% for ASIM EL NEHAR / Case Worker / Salary of January-2025 / 4.1 USD | I237: USD | J237: 4.1 | K237: 0.95749 | L237: =K237*J237 -> 3.925709 | N237: =YEAR(F237) -> 2025 | O237: =MONTH(F237) -> 1 | P237: 0
A238: 234 | B238: 1.1.17 | C238: S2511000011 | D238: PTT- USD | E238: PTT- USD | F238: 45688 | G238: PTT- USD | H238: PTT Transfer fees as 1% for NASER EL SEYH / Case Worker / Salary of January-2025 / 4.1 USD | I238: USD | J238: 4.1 | K238: 0.95749 | L238: =K238*J238 -> 3.925709 | N238: =YEAR(F238) -> 2025 | O238: =MONTH(F238) -> 1 | P238: 0
A239: 235 | B239: 1.1.17 | C239: S2511100054 | D239: PTT- USD | E239: PTT- USD | F239: 45716 | G239: PTT- USD | H239: PTT Fees as 1% of ASIM EL NEHAR / Case Worker / Salary of February-2025 Net Salary Paid by Bank / 4.1 USD | I239: USD | J239: 4.1 | K239: 0.96126 | L239: =K239*J239 -> 3.941166 | N239: =YEAR(F239) -> 2025 | O239: =MONTH(F239) -> 2 | P239: 0
A240: 236 | B240: 1.1.17 | C240: S2511000025 | D240: PTT- USD | E240: PTT- USD | F240: 45716 | G240: PTT- USD | H240: PTT Fees as 1% of MAISAA NAJJAR / Case Worker / Salary of February-2025 Net Salary Paid by Bank for 18 days / 2.46 USD | I240: USD | J240: 2.46 | K240: 0.96126 | L240: =K240*J240 -> 2.3646996 | N240: =YEAR(F240) -> 2025 | O240: =MONTH(F240) -> 2 | P240: 0
A241: 237 | B241: 1.1.17 | C241: S2500200500 | D241: Salary | E241: Salary | F241: 45716 | G241: MOHAMMAD ALAID ALSHAWI USD | H241: MOHAMMAD ALAID ALSHAWI / Salary of February-2025 Net Salary Paid by Bank for 13 days / 177.67 USD | I241: USD | J241: 177.67 | K241: 0.96126 | L241: =K241*J241 -> 170.78706 | N241: =YEAR(F241) -> 2025 | O241: =MONTH(F241) -> 2 | P241: 0
...

Sheet Project Budget in euros
A1: !!Please insert lines under the sub-headings if necessary!! !! Pay attention not to erase formulas in the blue cells !! | L1: Please check the totals in each column per year and the total in column G (Difference = 0)
A2: Name of the person in charge of the budget:
A3: Name of the applicant organisation:
A4: Project title:
B5: Instructions for filling in the Expenses column | C5: Expenditure related to the project | D5: Unit | E5: Number of units | F5: Unit cost (in €) | G5: Total cost (in €) | I5: Year 1 | J5: Year 2 | K5: Year 3 | L5: Total (I to K) for control purposes | M5: Discrepancy (with G column)
A6: 1 | C6: Human resources dedicated to the project
A7: 1.1 | C7: Salaries and employer's contributions
A8: 1.1.1 | B8: Indicate the staff position concerned | D8: per month | G8: =F8*E8 -> 0 | L8: =SUM(I8:K8) -> 0 | M8: =L8-G8 -> 0
A9: 1.1.2 | B9: Indicate the staff position concerned | D9: per month | G9: =F9*E9 -> 0 | L9: =SUM(I9:K9) -> 0 | M9: =L9-G9 -> 0
A10: 1.2 | C10: Expert's fees
A11: 1.2.1 | B11: Function of the expert | D11: per day | G11: =F11*E11 -> 0 | L11: =SUM(I11:K11) -> 0 | M11: =L11-G11 -> 0
A12: 1.2.2 | B12: Function of the expert | D12: per day | G12: =F12*E12 -> 0 | L12: =SUM(I12:K12) -> 0 | M12: =L12-G12 -> 0
A13: 1.3 | C13: Per diem food and accommodation costs
A14: 1.3.1 | B14: Purpose of the per diem expenditure | D14: per day | G14: =F14*E14 -> 0 | L14: =SUM(I14:K14) -> 0 | M14: =L14-G14 -> 0
A15: 1.3.2 | B15: Purpose of the per diem expenditure | D15: per day | G15: =F15*E15 -> 0 | L15: =SUM(I15:K15) -> 0 | M15: =L15-G15 -> 0
A16: Sub-total 1 Human resources for the project | G16: =SUM(G8:G15) -> 0 | I16: =SUM(I8:I15) -> 0 | J16: =SUM(J8:J15) -> 0 | K16: =SUM(K8:K15) -> 0 | L16: =SUM(I16:K16) -> 0 | M16: =L16-G16 -> 0
A17: 2 | C17: Travel
A18: 2.1 | B18: Purpose of the journey | D18: per trip | G18: =F18*E18 -> 0 | L18: =SUM(I18:K18) -> 0 | M18: =L18-G18 -> 0
A19: 2.2 | B19: Purpose of the journey | D19: per trip | G19: =F19*E19 -> 0 | L19: =SUM(I19:K19) -> 0 | M19: =L19-G19 -> 0
A20: Sub-total 2 Travel required for the project | G20: =SUM(G19,G18) -> 0 | I20: =SUM(I19,I18) -> 0 | J20: =SUM(J19,J18) -> 0 | K20: =SUM(K19,K18) -> 0 | L20: =SUM(I20:K20) -> 0 | M20: =L20-G20 -> 0
A21: 3 | C21: Equipment and supplies
A22: 3.1.1 | B22: Expenditure on equipment for the project | G22: =F22*E22 -> 0 | L22: =SUM(I22:K22) -> 0 | M22: =L22-G22 -> 0
A23: 3.1.2 | B23: Expenditure on equipment for the project | G23: =F23*E23 -> 0 | L23: =SUM(I23:K23) -> 0 | M23: =L23-G23 -> 0
A24: 3.2.1 | B24: Expenditure on equipment for the project | G24: =F24*E24 -> 0 | L24: =SUM(I24:K24) -> 0 | M24: =L24-G24 -> 0
A25: 3.2.2 | B25: Expenditure on equipment for the project | G25: =F25*E25 -> 0 | L25: =SUM(I25:K25) -> 0 | M25: =L25-G25 -> 0
A26: Sub-total 3 Equipment and supplies | G26: =SUM(G22:G25) -> 0 | I26: =SUM(I22:I25) -> 0 | J26: =SUM(J22:J25) -> 0 | K26: =SUM(K22:K25) -> 0 | L26: =SUM(I26:K26) -> 0 | M26: =L26-G26 -> 0
A27: 4 | C27: Other expenses
A28: 4.1 | B28: Type of expense (e.g. printing costs) | D28: per document | G28: =F28*E28 -> 0 | L28: =SUM(I28:K28) -> 0 | M28: =L28-G28 -> 0
A29: 4.2 | B29: Type of expense (e.g. rental of premises) | D29: per day | G29: =F29*E29 -> 0 | L29: =SUM(I29:K29) -> 0 | M29: =L29-G29 -> 0
A30: 4.3 | B30: Other expenses | G30: =F30*E30 -> 0 | L30: =SUM(I30:K30) -> 0 | M30: =L30-G30 -> 0
A31: 4.4 | G31: =F31*E31 -> 0 | L31: =SUM(I31:K31) -> 0 | M31: =L31-G31 -> 0
A32: 4.5 | G32: =F32*E32 -> 0 | L32: =SUM(I32:K32) -> 0 | M32: =L32-G32 -> 0
A33: Sub-total 4 Other expenses | G33: =SUM(G28:G32) -> 0 | I33: =SUM(I28:I32) -> 0 | J33: =SUM(J28:J32) -> 0 | K33: =SUM(K28:K32) -> 0 | L33: =SUM(I33:K33) -> 0 | M33: =L33-G33 -> 0
A34: Sub-total 5 Administrative costs | G34: =(G16+G20+G26+G33)*10% -> 0 | I34: =(I16+I20+I26+I33)*10% -> 0 | J34: =(J16+J20+J26+J33)*10% -> 0 | K34: =(K16+K20+K26+K33)*10% -> 0 | L34: =SUM(I34:K34) -> 0 | M34: =L34-G34 -> 0
A35: TOTAL DIRECT COST OF THE PROJECT (1 to 5) | G35: =SUM(G34,G33,G26,G20,G16) -> 0 | I35: =SUM(I34,I33,I26,I20,I16) -> 0 | J35: =SUM(J34,J33,J26,J20,J16) -> 0 | K35: =SUM(K34,K33,K26,K20,K16) -> 0 | L35: =SUM(I35:K35) -> 0 | M35: =L35-G35 -> 0
A37: FINANCING PLAN | D37: Requested | E37: Raised | F37: Percentage | G37: in € | I37: in € | J37: in € | K37: in € | L37: in € | M37: in €
A38: Grant requested (maximum 80% of the project) | F38: =G38/$G$45 -> #DIV/0! | L38: =SUM(I38:K38) -> 0 | M38: =L38-G38 -> 0
A39: Other donors (name) | F39: =G39/$G$45 -> #DIV/0! | L39: =SUM(I39:K39) -> 0 | M39: =L39-G39 -> 0
A40: Other donors (name) | F40: =G40/$G$45 -> #DIV/0! | L40: =SUM(I40:K40) -> 0 | M40: =L40-G40 -> 0
A41: Other donors (name) | F41: =G41/$G$45 -> #DIV/0! | L41: =SUM(I41:K41) -> 0 | M41: =L41-G41 -> 0
A42: Other donors (name) | F42: =G42/$G$45 -> #DIV/0! | L42: =SUM(I42:K42) -> 0 | M42: =L42-G42 -> 0
A43: Other donors (name) | F43: =G43/$G$45 -> #DIV/0! | L43: =SUM(I43:K43) -> 0 | M43: =L43-G43 -> 0
A44: Partners'contribution to the project | F44: =G44/$G$45 -> #DIV/0! | L44: =SUM(I44:K44) -> 0 | M44: =L44-G44 -> 0
A45: TOTAL RESOURCES | G45: =SUM(G38:G44) -> 0 | I45: =SUM(I38:I44) -> 0 | J45: =SUM(J38:J44) -> 0 | K45: =SUM(K38:K44) -> 0 | L45: =SUM(I45:K45) -> 0 | M45: =L45-G45 -> 0
A47: Check sum (total direct costs and total income must equal zero) | G47: =+G45-G35 -> 0 | I47: =+I45-I35 -> 0 | J47: =+J45-J35 -> 0 | K47: =+K45-K35 -> 0 | L47: =SUM(I47:K47) -> 0 | M47: =L47-G47 -> 0
